Workbook
Name tar_dur_1: 'Input Data'!$G$11
Name retirement_yr: Model!$C$220
Name dn_nw_10y: Model!$N$58
Name isa_limit: Model!$C$474
Name ann_rent_yield_2: 'Input Data'!$C$63
Name tar_amount_2: 'Input Data'!$E$13
Name tar_savings_2: 'Input Data'!$I$13
Name pa_tax_lb: 'Input Data'!$C$89
Name hal_mor_mp: 'Input Data'!$M$47
Name tar_date_2: 'Input Data'!$D$13
Name psy_fas: 'Input Data'!$F$41
Name tar_amount_3: 'Input Data'!$E$12
Name psy_rdm: 'Input Data'!$F$39
Name rent_util_2: 'Input Data'!$D$63
Name pens_ann_inc_gro: Model!$C$390
Name pa_tax_ub: 'Input Data'!$D$89
Name inv_lump_pct: Model!$C$431
Name year_birth: 'Input Data'!$B$2
Name edu_level: 'Input Data'!$B$7
Name hmrc_rate: 'Input Data'!$C$72
Name liv_sit: 'Input Data'!$B$4
Name rent_util_3: 'Input Data'!$D$64
Name ann_payment: Model!$C$135
Name br_tax_ub: 'Input Data'!$D$90
Name mon_debt_ir_1: #REF!
Name mon_payment_1: Model!$C$136
Name ann_th_salary: 'Input Data'!$E$22
Name ann_debt_ir_2: #REF!
Name uk_pen_gr: 'Input Data'!$C$70
Name mon_payment_2: #REF!
Name uk_min_wage: 'Input Data'!$C$71
Name ann_gross_sa: 'Input Data'!$C$21
Name psy_fop: 'Input Data'!$F$40
Name br_tax_lb: 'Input Data'!$C$90
Name hal_mor_apr_red: #REF!
Name tar_date_1: 'Input Data'!$D$11
Name br_tax_pct: 'Input Data'!$E$90
Name dn_nw_20y: Model!$AH$40
Name age: 'Input Data'!$B$3
Name msci_ann_div: 'Input Data'!$D$78
Name dn_nw_5y: Model!$I$58
Name hal_mor_apr: 'Input Data'!$L$47
Name ae_pen_mo: 'Input Data'!$L$39
Name down_payment: Model!$C$130
Name tar_dur_2: 'Input Data'!$G$13
Name mon_ni: 'Input Data'!$B$44
Name uk_lt_ir: 'Input Data'!$C$69
Name ann_exp: 'Input Data'!$C$37
Name ann_debt_ir_1: Model!$C$134
Name mon_exp: 'Input Data'!$B$37
Name ann_rent_yield_3: 'Input Data'!$C$64
Name hr_tax_lb: 'Input Data'!$C$91
Name tar_savings_1: 'Input Data'!$I$11
Name hous_dep: 'Input Data'!$B$5
Name ann_payment_2: #REF!
Name inv_cont_pct: Model!$C$473
Name dn_nw_bl: Model!$D$58
Name hr_tax_ub: 'Input Data'!$D$91
Name inv_bal_bl: 'Input Data'!$J$35
Name ar_tax_lb: 'Input Data'!$C$92

Sheet questionnaire_responses_rows
A1: id | B1: user_id | C1: first_name | D1: last_name | E1: email_address | F1: age_or_year_of_birth | G1: uk_location | H1: created_at | I1: updated_at | J1: current_living_situation | K1: highest_education_level | L1: living_arrangement | M1: additional_background_info | N1: current_work_situation | O1: monthly_take_home_salary | P1: other_income_sources | Q1: monthly_rent_mortgage | R1: monthly_bills_utilities | S1: monthly_transport | T1: monthly_subscriptions | U1: monthly_food_groceries | V1: monthly_leisure_entertainment | W1: monthly_other_expenses | X1: has_savings_accounts | Y1: savings_accounts | Z1: has_debts | AA1: debts | AB1: has_investment_platforms | AC1: investment_platforms | AD1: has_pension_accounts | AE1: pension_accounts | AF1: uses_tax_efficiency_methods | AG1: tax_efficiency_details | AH1: has_other_assets | AI1: other_assets | AJ1: has_automatic_plans | AK1: automatic_plans | AL1: has_emergency_fund | AM1: emergency_fund_months | AN1: emergency_fund_amount | AO1: has_dependents | AP1: dependents_details | AQ1: gross_annual_salary | AR1: net_monthly_salary | AS1: other_income_frequency | AT1: debt_total_amount | AU1: monthly_surplus | AV1: data_collection_date | AW1: monthly_rent_mortgage_numeric | AX1: monthly_bills_utilities_numeric | AY1: monthly_transport_numeric | AZ1: monthly_subscriptions_numeric | BA1: monthly_food_groceries_numeric | BB1: monthly_leisure_entertainment_numeric | BC1: monthly_other_expenses_numeric | BD1: emergency_fund_amount_numeric | BE1: country | BF1: city | BG1: investment_service_providers | BH1: other_income_amount
A2: 529278c1-e6bb-4ee4-a877-1436b5c84840 | C2: Alpha | D2: 2 | F2: 34 | H2: 2025-05-28 12:01:18.565955+00 | I2: 2025-05-28 12:01:18.565955+00 | J2: own-mortgage | K2: undergraduate | L2: live-with-family | N2: unemployed | O2: 9000 | P2: None | Q2: 817 | R2: 350 | S2: 200 | T2: 25 | U2: 900 | V2: 250 | W2: 0 | X2: no | Y2: [{"bank": "", "balance": "", "interestRate": ""}] | Z2: yes | AA2: [{"type": "mortgage", "provider": "Lloyds", "customType": "", "interestRate": "1.46", "monthlyPayment": "2220.87", "outstandingBalance": "346257"}] | AB2: yes | AC2: [{"provider": "Charles Stanley", "totalValue": "111,104", "accountType": "ISA", "monthlyContribution": "", "performanceLastYear": "1.49%"}] | AD2: yes | AE2: [{"type": "workplace", "provider": "L&G", "currentValue": "53755.57", "monthlyContribution": "0"}, {"type": "workplace", "provider": "L&G", "currentValue": "57674.1", "monthlyContribution": ""}] | AF2: yes | AI2: [] | AJ2: FALSE | AK2: [] | AO2: no | AP2: [] | AQ2: 108000 | AR2: 9000 | AT2: 0 | AU2: 6458 | AV2: 2025-05-28 12:01:17.182+00 | AW2: 817 | AX2: 350 | AY2: 200 | AZ2: 25 | BA2: 900 | BB2: 250 | BC2: 0 | BE2: England | BF2: London | BG2: [] | BH2: 0

Sheet Data
A1: Time Horizon | B1: Category | C1: Goal | D1: Calculation | E1: 1 | F1: Helpers | W1: Dates
A2: Short-Term | B2: Career & Education | C2: Launching a Venture / Franchise | D2: savings target | E2: A. | F2: {=UNIQUE(Data!A2:A1000)} -> Short-Term | G2: B. | H2: {=UNIQUE(Data!B2:B1000)} -> Career & Education | I2: C. | J2: =IFERROR(__xludf.DUMMYFUNCTION("SORT(UNIQUE(FILTER(Data!C2:C1000, (Data!B2:B1000 = 'Input Data'!B11))))"),"Buying a Car") -> Buying a Car | K2: A. | L2: {=UNIQUE(Data!A2:A1000)} -> Short-Term | M2: B. | N2: {=UNIQUE(Data!B2:B1000)} -> Career & Education | O2: C. | P2: =IFERROR(__xludf.DUMMYFUNCTION("SORT(UNIQUE(FILTER(Data!C2:C1000, (Data!B2:B1000 = 'Input Data'!B13))))"),"Building an Investment Portfolio") -> Building an Investment Portfolio | Q2: A. | R2: {=UNIQUE(Data!A2:A1000)} -> Short-Term | S2: B. | T2: {=UNIQUE(Data!B2:B1000)} -> Career & Education | U2: C. | V2: =IFERROR(__xludf.DUMMYFUNCTION("SORT(UNIQUE(FILTER(Data!C2:C1000, (Data!B2:B1000 = 'Input Data'!B12))))"),"Building a Safety Net") -> Building a Safety Net
A3: Medium-Term | B3: Career & Education | C3: Master’s Degree or Further Study | D3: savings target | F3: Medium-Term | H3: Essentials | J3: =IFERROR(__xludf.DUMMYFUNCTION("""COMPUTED_VALUE"""),"Buying a Property") -> Buying a Property | L3: Medium-Term | N3: Essentials | P3: =IFERROR(__xludf.DUMMYFUNCTION("""COMPUTED_VALUE"""),"Financial Independence (FIRE goals)") -> Financial Independence (FIRE goals) | R3: Medium-Term | T3: Essentials | V3: =IFERROR(__xludf.DUMMYFUNCTION("""COMPUTED_VALUE"""),"Paying off Loan") -> Paying off Loan
A4: Long-Term | B4: Career & Education | C4: Starting a Business (scaled-up funding) | D4: savings target | F4: Long-Term | H4: Family & Legacy | J4: =IFERROR(__xludf.DUMMYFUNCTION("""COMPUTED_VALUE"""),"Furniture or Home Decor") -> Furniture or Home Decor | L4: Long-Term | N4: Family & Legacy | P4: =IFERROR(__xludf.DUMMYFUNCTION("""COMPUTED_VALUE"""),"Pension Top-Up Plan") -> Pension Top-Up Plan | R4: Long-Term | T4: Family & Legacy | V4: =IFERROR(__xludf.DUMMYFUNCTION("""COMPUTED_VALUE"""),"Saving for a Career Break or Sabbatical") -> Saving for a Career Break or Sabbatical
A5: N/A | B5: Career & Education | C5: Professional Qualification or Certification | D5: savings target | F5: N/A | H5: Financial Stability | J5: =IFERROR(__xludf.DUMMYFUNCTION("""COMPUTED_VALUE"""),"Paying Off Mortgage Early") -> Paying Off Mortgage Early | L5: N/A | N5: Financial Stability | P5: =IFERROR(__xludf.DUMMYFUNCTION("""COMPUTED_VALUE"""),"Retirement Savings") -> Retirement Savings | R5: N/A | T5: Financial Stability
B6: Career & Education | C6: Course or Training Fees | D6: savings target | H6: Lifestyle & Leisure | J6: =IFERROR(__xludf.DUMMYFUNCTION("""COMPUTED_VALUE"""),"Saving for a House Deposit") -> Saving for a House Deposit | N6: Lifestyle & Leisure | T6: Lifestyle & Leisure
B7: Career & Education | C7: Laptop / Tools for Work | D7: savings target | H7: Property & Real Estate | N7: Property & Real Estate | T7: Property & Real Estate
B8: Career & Education | C8: Starting a Business (initial expenses) | D8: savings target | H8: N/A | N8: N/A | T8: N/A
B9: Essentials | C9: Emergency Fund | D9: savings target | H9: Retirement & Future Security | N9: Retirement & Future Security | T9: Retirement & Future Security
B10: Essentials | C10: Rent Deposit / Moving Costs | D10: savings target
B11: Essentials | C11: Paying off Credit Card Debt
B12: Essentials | C12: Paying off Buy Now Pay Later (BNPL)
B13: Essentials | C13: Paying off Overdraft
B14: Essentials | C14: Covering Annual Bills | D14: savings target
B15: Family & Legacy | C15: Child’s Education Fund
B16: Family & Legacy | C16: Childcare Savings
B17: Family & Legacy | C17: Inheritance Planning
B18: Family & Legacy | C18: Philanthropy / Charity Fund
B19: Family & Legacy | C19: Wedding Fund
B20: Family & Legacy | C20: IVF or Fertility Treatment
B21: Family & Legacy | C21: Having a Baby (preparation costs)
B22: Family & Legacy | C22: Supporting a Partner or Relative
B23: Financial Stability | C23: Paying off Loan
B24: Financial Stability | C24: Building a Safety Net
B25: Financial Stability | C25: Saving for a Career Break or Sabbatical
B26: Lifestyle & Leisure | C26: Extended Travel / Gap Year
... B41: Retirement & Future Security | C41: Building an Investment Portfolio

Sheet Input Data
A1: Customer data
A2: Year of birth | B2: =if(questionnaire_responses_rows!F2 >1000,questionnaire_responses_rows!F2,-(questionnaire_responses_rows!F2-year(today()))) -> 1991 | C2: =B2+70 -> 2061 | D2: =C2-2025 -> 36
A3: Age | B3: =if(questionnaire_responses_rows!F2 <1000,questionnaire_responses_rows!F2,year(today())-questionnaire_responses_rows!F2) -> 34
A4: Living situation | B4: =questionnaire_responses_rows!L2 -> live-with-family
A5: Household Dependents? | B5: =questionnaire_responses_rows!AO2 -> no
A6: Job status | B6: =questionnaire_responses_rows!N2 -> unemployed
A7: Education level | B7: =questionnaire_responses_rows!K2 -> undergraduate
A9: Financial goals
A10: Timeline | B10: Category | C10: Goal | D10: Target Date formatted as (DD/MM/YYYY) | E10: Target total (must be a number) | F10: Target Amount Frequency | G10: Duration | I10: Savings Already Allocated | J10: Priority | K10: Additional Details (mortgage interest rate, etc.)
A11: Medium-Term | B11: Property & Real Estate | C11: Buying a Property | D11: 46023 | E11: 600000 | F11: Monthly | G11: 25 | H11: Years | I11: 0 | J11: High
A12: Short-Term | B12: Financial Stability | C12: Saving for a Career Break or Sabbatical | D12: 46022 | E12: 15800 | F12: Monthly | G12: 6 | H12: Months | I12: 0 | J12: High
A13: Long-Term | B13: Retirement & Future Security | C13: Retirement Savings | D13: 58987 | E13: 50000 | F13: Annually | G13: 36 | H13: Years | I13: 0 | J13: Medium
A16: Income & Expenses | I16: Assets & Debts
A18: Income | I18: Current & Savings accounts
A20: Income source | B20: Payment Frequency | C20: Annual Gross Salary | D20: Net Monthly Salary | E20: Annual Takehome Salary
A21: Salary | B21: Monthly | C21: =questionnaire_responses_rows!AQ2 -> 108000 | D21: =questionnaire_responses_rows!AR2 -> 9000 | E21: =D21*12 -> 108000 | I21: Account type | J21: Provider | K21: Balance | L21: Interest Rate (%) | M21: Last year dividends (%) | N21: Last year dividends (%)
A22: Additional | B22: NA | C22: 0 | D22: =sum(D21) -> 9000 | E22: =sum(E21) -> 108000 | I22: Cash/ savings account 1 | J22: =PARSEJSONDATA(questionnaire_responses_rows!Y2)
A23: Total income minus tax | I23: Cash/ savings account 2
I24: Cash/ savings account 3
I25: Cash/ savings account 4
I26: Cash/ savings account 5
A27: Expenses (monthly) | I27: Total | K27: =SUM(K22:K26) -> 0 | L27: =SUMPRODUCT(K22:K26,L22:L26)/SUM($K22:$K26) -> #DIV/0! | M27: =SUMPRODUCT($K22:$K26,M22:M26)/SUM($K22:$K26) -> #DIV/0! | N27: =SUMPRODUCT($K22:$K26,N22:N26)/SUM($K22:$K26) -> #DIV/0!
E28: Dependent Details
A29: =questionnaire_responses_rows!J2 -> own-mortgage | B29: Monthly | C29: Annual | E29: Age | F29: Relationship | G29: Financial Support | I29: Investment accounts
A30: =IF(ISNUMBER(SEARCH("mortgage", questionnaire_responses_rows!J2)), "Mortgage", "Rent") -> Mortgage | B30: =questionnaire_responses_rows!Q2 -> 817 | C30: =B30*12 -> 9804 | E30: =PARSEJSONDATA(questionnaire_responses_rows!AP2) -> #ERROR! | I30: Provider | J30: Balance | K30: Account type | L30: Monthly Contributions | M30: Last year growth rate (%) | N30: Last year dividends (%)
A31: Utilities | B31: =questionnaire_responses_rows!R2 -> 350 | C31: =B31*12 -> 4200 | I31: =PARSEJSONDATA(questionnaire_responses_rows!AC2) -> Charles Stanley | J31: 111104 | K31: ISA | M31: 1.49
A32: Transport | B32: =questionnaire_responses_rows!S2 -> 200 | C32: =B32*12 -> 2400
A33: Subscriptions | B33: =questionnaire_responses_rows!T2 -> 25 | C33: =B33*12 -> 300
A34: Food and Groceries | B34: =questionnaire_responses_rows!U2 -> 900 | C34: =B34*12 -> 10800
A35: Leisure and Entertainment | B35: =questionnaire_responses_rows!V2 -> 250 | C35: =B35*12 -> 3000 | I35: Total | J35: =SUM(J28:J34) -> 111104 | L35: =SUM(L30:L34) -> 0
A36: Other regular expenses | B36: =questionnaire_responses_rows!W2 -> 0 | C36: =B36*12 -> 0
A37: Total expenses | B37: =sum(B30:B36) -> 2542 | C37: =B37*12 -> 30504 | E37: Psychographic assessment | I37: Pension accounts
E38: Indicator | F38: Score (/5) | I38: Account type | J38: Provider | K38: Balance | L38: Monthly Contributions | M38: Last year growth rate (%) | N38: Last year dividends (%)
E39: Risk & Decision-making | F39: 3.68 | I39: =PARSEJSONDATA(questionnaire_responses_rows!AE2) -> workplace | J39: L&G | K39: 53755.57 | L39: 0
E40: Future Orientation & Planning | F40: 5 | I40: workplace | J40: L&G | K40: 57674.1
E41: Financial Awareness & Stability | F41: 4.13
B43: Monthly | C43: Annual | I43: Total | K43: =SUM(K36:K42) -> 111429.67 | L43: =SUM(L38:L42) -> 0
A44: Net income | B44: =D22-B37 -> 6458 | C44: =B44*12 -> 77496
I45: Debts
E46: Property Estimation Tool | I46: Debt type | J46: Provider | K46: Custom Type | L46: APR (%) | M46: Monthly payment | N46: Outstanding balance
A47: Automations/ additional notes | E47: Variable | F47: Estimated Value (2025) | G47: Notes | I47: =PARSEJSONDATA(questionnaire_responses_rows!AA2) -> mortgage | J47: Lloyds | L47: 1.46 | M47: 2220.87 | N47: 346257
E48: Mortgage | F48: 1200000 | G48: UK average per household with a mortgage
A49: =questionnaire_responses_rows!M2 | E49: Average Mortgage Interest Rate | F49: 0.0424 | G49: https://www.uswitch.com/mortgages/uk-mortgage-rates-today/
A50: ="Tax Efficiency: "&questionnaire_responses_rows!AG2 -> Tax Efficiency: | E50: Median Monthly Mortgage Payment
E51: Months since purchase | F51: 0
A52: ="Other Income Sources: "&questionnaire_responses_rows!P2 -> Other Income Sources: None | E52: Median Home Value Growth Rate | F52: 0.033 | G52: https://www.ons.gov.uk/economy/inflationandpriceindices/bulletins/privaterentandhousepricesuk/june2025 | I52: Total | L52: =SUMPRODUCT($N46:$N50,L46:L50)/SUM($N46:$N50) -> 1.46 | M52: =SUM(M46:M50) -> 2220.87 | N52: =SUM(N44:N50) -> 346257
E53: Typical LTV at Origination | F53: 0.6 | G53: Majority of new UK mortgages
E54: Estimated Original Mortage Value | F54: =-Round(PV((4.54%/12),F51,F50,F48),-5) -> 1200000 | G54: Assumed based on current value (assuming 2 years of payments)
E55: Estimated Original Property Value | F55: 1200000
E56: Estimated Current Property Value | F56: =-FV((F52/12),F51,0,F55) -> 1200000 | I56: Total asset value today | J56: =K27+J35+K43 -> 222533.67
A57: Benchmarks and external data
I58: Total debt value today | J58: =N52 -> 346257
A59: Property yields
B61: Rental property | C61: Annual rental yield | D61: % utilization (rented out) | E61: Source
B62: N/A | C62: 0 | D62: 0 | E62: https://www.rpagroupllc.com/news/uk-market-report-april-2025
B63: N/A | C63: 0 | D63: 0
B64: N/A | C64: 0 | D64: 0
A66: Central bank interest rates
B68: Rate used | C68: % | D68: Source
B69: UK long-term interest rate minus 50 bps (bank profit margin) | C69: 0.035 | D69: https://www.capitaleconomics.com/uk/lower-gdp-growth-and-cpi-inflation-most-expect-lead-more-interest-rate-cuts
B70: Pension growth rate | C70: 0.08 | D70: https://www.pensionbee.com/uk/press/another-strong-year-in-2025
B71: UK minimum wage | C71: =12.21*52*5*8 -> 25396.8 | D71: https://www.gov.uk/national-minimum-wage-rates
B72: HMRC top-up rate | C72: 0.25
A75: Equity benchmarks
B76: Benchmark index/ ETF | C76: Rate used | D76: % | E76: Source
B77: MSCI GBP (URTH) | C77: Annual growth rate (GBP) | D77: 0.0717 | E77: 26-year historic rate for MSCI GBP
B78: MSCI GBP (URTH) | C78: Annual dividends paid out | D78: 0.0136 | E78: Forward dividend yield rate
B79: S&P 500 (VOO) | C79: Annual growth rate (GBP) | D79: 0.1017 | E79: 10-Year CAGR
B80: S&P 500 (VOO) | C80: Annual dividends paid out | D80: 0.0173 | E80: VOO long term dividend yield
A84: UK Income Tax bands
A86: Source | B86: https://www.gov.uk/income-tax-rates
B88: Band | C88: Taxable income (lower bound) | D88: Taxable income (upper bound) | E88: Tax rate
B89: Personal allowance | C89: 0 | D89: 12750 | E89: 0
B90: Basic rate | C90: 12571 | D90: 50270 | E90: 0.2
B91: Higher rate | C91: 50271 | D91: 125140 | E91: 0.4
B92: Additional rate | C92: 125141 | D92: NA | E92: 0.45

Sheet Model
A1: 0 | B1: Do-Nothing Scenario
B3: Assumptions | C3: No changes are made to income/expenses
C4: Goals are not yet considered
B7: Net income by year
B9: Income | C9: Interest/ growth rates | D9: Baseline June 2025 | E9: 46143 | F9: 46508 | G9: 46874 | H9: 47239 | I9: 47604 | J9: 47969 | K9: 48335 | L9: 48700 | M9: 49065 | N9: 49430 | O9: 49796 | P9: 50161 | Q9: 50526 | R9: 50891 | S9: 51257 | T9: 51622 | U9: 51987 | V9: 52352 | W9: 52718 | X9: 53083 | Y9: 53448 | Z9: 53813 | AA9: 54179 | AB9: 54544 | AC9: 54909 | AD9: 55274 | AE9: 55640 | AF9: 56005 | AG9: 56370 | AH9: 56735 | AI9: 57101 | AJ9: 57466 | AK9: 57831 | AL9: 58196 | AM9: 58562 | AN9: 58927 | AO9: 59292 | AP9: 59657 | AQ9: 60023 | AR9: 60388 | AS9: 60753 | AT9: 61118 | AU9: 61484 | AV9: 61849 | AW9: 62214 | AX9: 62579 | AY9: 62945 | AZ9: 63310
B10: Total take home salary | C10: 0 | D10: 54000 | E10: =ann_th_salary -> 108000 | F10: =ann_th_salary -> 108000 | G10: =ann_th_salary -> 108000 | H10: =ann_th_salary -> 108000 | I10: =ann_th_salary -> 108000 | J10: =ann_th_salary -> 108000 | K10: =ann_th_salary -> 108000 | L10: =ann_th_salary -> 108000 | ... AZ10: =ann_th_salary -> 108000
B11: Total dividend income | C11: 0 | D11: =D33*$C11 -> 0 | E11: =E33*$C11 -> 0 | F11: =F33*$C11 -> 0 | G11: =G33*$C11 -> 0 | H11: =H33*$C11 -> 0 | I11: =I33*$C11 -> 0 | J11: =J33*$C11 -> 0 | K11: =K33*$C11 -> 0 | ... AZ11: =AZ33*$C11 -> 0
B12: Total expenses (inc. mortgage) | C12: 0 | D12: =ann_exp+('Input Data'!$M$52*12) -> 57154.44 | E12: =ann_exp+('Input Data'!$M$52*12) -> 57154.44 | F12: =ann_exp+('Input Data'!$M$52*12) -> 57154.44 | G12: =ann_exp+('Input Data'!$M$52*12) -> 57154.44 | H12: =ann_exp+('Input Data'!$M$52*12) -> 57154.44 | I12: =ann_exp+('Input Data'!$M$52*12) -> 57154.44 | J12: =ann_exp+('Input Data'!$M$52*12) -> 57154.44 | K12: =ann_exp+('Input Data'!$M$52*12) -> 57154.44 | ... AZ12: =ann_exp+('Input Data'!$M$52*12) -> 57154.44
B13: Expenses % salary | D13: =iferror(D12/D10,"N/A") -> 1.0584156 | E13: =iferror(E12/E10,"N/A") -> 0.52920778 | F13: =iferror(F12/F10,"N/A") -> 0.52920778 | G13: =iferror(G12/G10,"N/A") -> 0.52920778 | H13: =iferror(H12/H10,"N/A") -> 0.52920778 | I13: =iferror(I12/I10,"N/A") -> 0.52920778 | J13: =iferror(J12/J10,"N/A") -> 0.52920778 | K13: =iferror(K12/K10,"N/A") -> 0.52920778 | ... AZ13: =iferror(AZ12/AZ10,"N/A") -> 0.52920778
B14: Net income | D14: =sum(D10:D11)-D12 -> -3154.44 | E14: =sum(E10:E11)-E12 -> 50845.56 | F14: =sum(F10:F11)-F12 -> 50845.56 | G14: =sum(G10:G11)-G12 -> 50845.56 | H14: =sum(H10:H11)-H12 -> 50845.56 | I14: =sum(I10:I11)-I12 -> 50845.56 | J14: =sum(J10:J11)-J12 -> 50845.56 | K14: =sum(K10:K11)-K12 -> 50845.56 | ... AZ14: =sum(AZ10:AZ11)-AZ12 -> 50845.56
B15: Income allocation to savings | C15: 1 | D15: =$C15*D$14 -> -3154.44 | E15: =$C15*E$14 -> 50845.56 | F15: =$C15*F$14 -> 50845.56 | G15: =$C15*G$14 -> 50845.56 | H15: =$C15*H$14 -> 50845.56 | I15: =$C15*I$14 -> 50845.56 | J15: =$C15*J$14 -> 50845.56 | K15: =$C15*K$14 -> 50845.56 | ... AZ15: =$C15*AZ$14 -> 50845.56
B16: Income allocation to investments | C16: 0 | D16: =$C16*D$15 -> 0 | E16: =$C16*E$15 -> 0 | F16: =$C16*F$15 -> 0 | G16: =$C16*G$15 -> 0 | H16: =$C16*H$15 -> 0 | I16: =$C16*I$15 -> 0 | J16: =$C16*J$15 -> 0 | K16: =$C16*K$15 -> 0 | ... AZ16: =$C16*AZ$15 -> 0
B18: Net wealth by year
B20: Assets | C20: Interest/ growth rates | D20: Baseline June 2025 | E20: 46143 | F20: 46508 | G20: 46874 | H20: 47239 | I20: 47604 | J20: 47969 | K20: 48335 | L20: 48700 | M20: 49065 | N20: 49430 | O20: 49796 | P20: 50161 | Q20: 50526 | R20: 50891 | S20: 51257 | T20: 51622 | U20: 51987 | V20: 52352 | W20: 52718 | X20: 53083 | Y20: 53448 | Z20: 53813 | AA20: 54179 | AB20: 54544 | AC20: 54909 | AD20: 55274 | AE20: 55640 | AF20: 56005 | AG20: 56370 | AH20: 56735 | AI20: 57101 | AJ20: 57466 | AK20: 57831 | AL20: 58196 | AM20: 58562 | AN20: 58927 | AO20: 59292 | AP20: 59657 | AQ20: 60023 | AR20: 60388 | AS20: 60753 | AT20: 61118 | AU20: 61484 | AV20: 61849 | AW20: 62214 | AX20: 62579 | AY20: 62945 | AZ20: 63310
B21: Cash/ savings accounts
B22: Account 1 | C22: ='Input Data'!L22 | D22: ='Input Data'!K22 | E22: =D22*(1+$C22)+D14*$C$15 -> -3154.44 | F22: =E22*(1+$C22)+E14*$C$15 -> 47691.12 | G22: =F22*(1+$C22)+F14*$C$15 -> 98536.68 | H22: =G22*(1+$C22)+G14*$C$15 -> 149382.24 | I22: =H22*(1+$C22)+H14*$C$15 -> 200227.8 | J22: =I22*(1+$C22)+I14*$C$15 -> 251073.36 | K22: =J22*(1+$C22)+J14*$C$15 -> 301918.92 | L22: =K22*(1+$C22)+K14*$C$15 -> 352764.48 | ... AZ22: =AY22*(1+$C22)+AY14*$C$15 -> 2386586.9
B23: Account 2 | C23: ='Input Data'!L23 | D23: ='Input Data'!K23 | E23: =D23*(1+$C23) -> 0 | F23: =E23*(1+$C23) -> 0 | G23: =F23*(1+$C23) -> 0 | H23: =G23*(1+$C23) -> 0 | I23: =H23*(1+$C23) -> 0 | J23: =I23*(1+$C23) -> 0 | K23: =J23*(1+$C23) -> 0 | L23: =K23*(1+$C23) -> 0 | ... AZ23: =AY23*(1+$C23) -> 0
B24: Account 3 | C24: ='Input Data'!L24 | D24: ='Input Data'!K24 | E24: =D24*(1+$C24) -> 0 | F24: =E24*(1+$C24) -> 0 | G24: =F24*(1+$C24) -> 0 | H24: =G24*(1+$C24) -> 0 | I24: =H24*(1+$C24) -> 0 | J24: =I24*(1+$C24) -> 0 | K24: =J24*(1+$C24) -> 0 | L24: =K24*(1+$C24) -> 0 | ... AZ24: =AY24*(1+$C24) -> 0
B25: Account 4 | C25: ='Input Data'!L25 | D25: ='Input Data'!K25 | E25: =D25*(1+$C25) -> 0 | F25: =E25*(1+$C25) -> 0 | G25: =F25*(1+$C25) -> 0 | H25: =G25*(1+$C25) -> 0 | I25: =H25*(1+$C25) -> 0 | J25: =I25*(1+$C25) -> 0 | K25: =J25*(1+$C25) -> 0 | L25: =K25*(1+$C25) -> 0 | ... AZ25: =AY25*(1+$C25) -> 0
B26: Account 5 | C26: ='Input Data'!L26 | D26: ='Input Data'!K26 | E26: =D26*(1+$C26) -> 0 | F26: =E26*(1+$C26) -> 0 | G26: =F26*(1+$C26) -> 0 | H26: =G26*(1+$C26) -> 0 | I26: =H26*(1+$C26) -> 0 | J26: =I26*(1+$C26) -> 0 | K26: =J26*(1+$C26) -> 0 | L26: =K26*(1+$C26) -> 0 | ... AZ26: =AY26*(1+$C26) -> 0
B27: Cash/ savings total | C27: =iferror(sumproduct(C22:C26,D22:D26)/D27,"N/A") -> N/A | D27: =subtotal(9,D22:D26) -> 0 | E27: =subtotal(9,E22:E26) -> -3154.44 | F27: =subtotal(9,F22:F26) -> 47691.12 | G27: =subtotal(9,G22:G26) -> 98536.68 | H27: =subtotal(9,H22:H26) -> 149382.24 | I27: =subtotal(9,I22:I26) -> 200227.8 | J27: =subtotal(9,J22:J26) -> 251073.36 | K27: =subtotal(9,K22:K26) -> 301918.92 | ... AZ27: =subtotal(9,AZ22:AZ26) -> 2386586.9
B28: Investment accounts
B29: ='Input Data'!I31 -> Charles Stanley | C29: =msci_ann_gr -> 0.0717 | D29: ='Input Data'!J31 -> 111104 | E29: =D29*(1+$C29)+'Input Data'!$L31 -> 119070.16 | F29: =E29*(1+$C29)+'Input Data'!$L31 -> 127607.49 | G29: =F29*(1+$C29)+'Input Data'!$L31 -> 136756.94 | H29: =G29*(1+$C29)+'Input Data'!$L31 -> 146562.42 | I29: =H29*(1+$C29)+'Input Data'!$L31 -> 157070.94 | J29: =I29*(1+$C29)+'Input Data'!$L31 -> 168332.93 | K29: =J29*(1+$C29)+'Input Data'!$L31 -> 180402.4 | L29: =K29*(1+$C29)+'Input Data'!$L31 -> 193337.25 | ... AZ29: =AY29*(1+$C29)+'Input Data'!$L31 -> 3084926.1
B30: ='Input Data'!I32 | C30: =msci_ann_gr -> 0.0717 | E30: =D30*(1+$C30)+'Input Data'!$L32 -> 0 | F30: =E30*(1+$C30)+'Input Data'!$L32 -> 0 | G30: =F30*(1+$C30)+'Input Data'!$L32 -> 0 | H30: =G30*(1+$C30)+'Input Data'!$L32 -> 0 | I30: =H30*(1+$C30)+'Input Data'!$L32 -> 0 | J30: =I30*(1+$C30)+'Input Data'!$L32 -> 0 | K30: =J30*(1+$C30)+'Input Data'!$L32 -> 0 | L30: =K30*(1+$C30)+'Input Data'!$L32 -> 0 | ... AZ30: =AY30*(1+$C30)+'Input Data'!$L32 -> 0
B31: ='Input Data'!I33 | C31: =msci_ann_gr -> 0.0717 | E31: =D31*(1+$C31)+'Input Data'!$L33 -> 0 | F31: =E31*(1+$C31)+'Input Data'!$L33 -> 0 | G31: =F31*(1+$C31)+'Input Data'!$L33 -> 0 | H31: =G31*(1+$C31)+'Input Data'!$L33 -> 0 | I31: =H31*(1+$C31)+'Input Data'!$L33 -> 0 | J31: =I31*(1+$C31)+'Input Data'!$L33 -> 0 | K31: =J31*(1+$C31)+'Input Data'!$L33 -> 0 | L31: =K31*(1+$C31)+'Input Data'!$L33 -> 0 | ... AZ31: =AY31*(1+$C31)+'Input Data'!$L33 -> 0
B32: ='Input Data'!I34 | C32: =msci_ann_gr -> 0.0717 | E32: =D32*(1+$C32)+'Input Data'!$L34 -> 0 | F32: =E32*(1+$C32)+'Input Data'!$L34 -> 0 | G32: =F32*(1+$C32)+'Input Data'!$L34 -> 0 | H32: =G32*(1+$C32)+'Input Data'!$L34 -> 0 | I32: =H32*(1+$C32)+'Input Data'!$L34 -> 0 | J32: =I32*(1+$C32)+'Input Data'!$L34 -> 0 | K32: =J32*(1+$C32)+'Input Data'!$L34 -> 0 | L32: =K32*(1+$C32)+'Input Data'!$L34 -> 0 | ... AZ32: =AY32*(1+$C32)+'Input Data'!$L34 -> 0
B33: Investments total | C33: =AVERAGE(C29:C32) -> 0.0717 | D33: =subtotal(9,D29:D32) -> 111104 | E33: =subtotal(9,E29:E32) -> 119070.16 | F33: =subtotal(9,F29:F32) -> 127607.49 | G33: =subtotal(9,G29:G32) -> 136756.94 | H33: =subtotal(9,H29:H32) -> 146562.42 | I33: =subtotal(9,I29:I32) -> 157070.94 | J33: =subtotal(9,J29:J32) -> 168332.93 | K33: =subtotal(9,K29:K32) -> 180402.4 | ... AZ33: =subtotal(9,AZ29:AZ32) -> 3084926.1
B34: Pension accounts
B35: ='Input Data'!J39 -> L&G | C35: =msci_ann_gr -> 0.0717 | D35: ='Input Data'!K39 -> 53755.57 | E35: =D35*(1+$C35)+'Input Data'!$L39 -> 57609.844 | F35: =E35*(1+$C35)+'Input Data'!$L39 -> 61740.47 | G35: =F35*(1+$C35)+'Input Data'!$L39 -> 66167.262 | H35: =G35*(1+$C35)+'Input Data'!$L39 -> 70911.455 | I35: =H35*(1+$C35)+'Input Data'!$L39 -> 75995.806 | J35: =I35*(1+$C35)+'Input Data'!$L39 -> 81444.705 | K35: =J35*(1+$C35)+'Input Data'!$L39 -> 87284.291 | L35: =K35*(1+$C35)+'Input Data'!$L39 -> 93542.574 | ... AZ35: =AY35*(1+$C35)+'Input Data'!$L39 -> 1492583.2
B36: ='Input Data'!J40 -> L&G | C36: =msci_ann_gr -> 0.0717 | D36: ='Input Data'!K40 -> 57674.1 | E36: =D36*(1+$C36)+'Input Data'!$L40 -> 61809.333 | F36: =E36*(1+$C36)+'Input Data'!$L40 -> 66241.062 | G36: =F36*(1+$C36)+'Input Data'!$L40 -> 70990.546 | H36: =G36*(1+$C36)+'Input Data'!$L40 -> 76080.568 | I36: =H36*(1+$C36)+'Input Data'!$L40 -> 81535.545 | J36: =I36*(1+$C36)+'Input Data'!$L40 -> 87381.644 | K36: =J36*(1+$C36)+'Input Data'!$L40 -> 93646.908 | L36: =K36*(1+$C36)+'Input Data'!$L40 -> 100361.39 | ... AZ36: =AY36*(1+$C36)+'Input Data'!$L40 -> 1601385.5
B37: ='Input Data'!J41 | C37: =msci_ann_gr -> 0.0717 | D37: ='Input Data'!K41 | E37: =D37*(1+C37)+'Input Data'!$L41 -> 0 | F37: =E37*(1+$C37)+'Input Data'!$L41 -> 0 | G37: =F37*(1+$C37)+'Input Data'!$L41 -> 0 | H37: =G37*(1+$C37)+'Input Data'!$L41 -> 0 | I37: =H37*(1+$C37)+'Input Data'!$L41 -> 0 | J37: =I37*(1+$C37)+'Input Data'!$L41 -> 0 | K37: =J37*(1+$C37)+'Input Data'!$L41 -> 0 | L37: =K37*(1+$C37)+'Input Data'!$L41 -> 0 | M37: =L37*(1+$C37)+'Input Data'!$L41 -> 0 | ... AZ37: =AY37*(1+$C37)+'Input Data'!$L41 -> 0
B38: ='Input Data'!J42 | C38: =msci_ann_gr -> 0.0717 | D38: ='Input Data'!K42 | E38: =D38*(1+C38)+'Input Data'!$L42 -> 0 | F38: =E38*(1+$C38)+'Input Data'!$L42 -> 0 | G38: =F38*(1+$C38)+'Input Data'!$L42 -> 0 | H38: =G38*(1+$C38)+'Input Data'!$L42 -> 0 | I38: =H38*(1+$C38)+'Input Data'!$L42 -> 0 | J38: =I38*(1+$C38)+'Input Data'!$L42 -> 0 | K38: =J38*(1+$C38)+'Input Data'!$L42 -> 0 | L38: =K38*(1+$C38)+'Input Data'!$L42 -> 0 | M38: =L38*(1+$C38)+'Input Data'!$L42 -> 0 | ... AZ38: =AY38*(1+$C38)+'Input Data'!$L42 -> 0
B39: Pensions total | D39: =subtotal(9,D35:D38) -> 111429.67 | E39: =subtotal(9,E35:E38) -> 119419.18 | F39: =subtotal(9,F35:F38) -> 127981.53 | G39: =subtotal(9,G35:G38) -> 137157.81 | H39: =subtotal(9,H35:H38) -> 146992.02 | I39: =subtotal(9,I35:I38) -> 157531.35 | J39: =subtotal(9,J35:J38) -> 168826.35 | K39: =subtotal(9,K35:K38) -> 180931.2 | ... AZ39: =subtotal(9,AZ35:AZ38) -> 3093968.7
B40: Liquid Assets Total | D40: =D27+D33+D39 -> 222533.67 | E40: =E27+E33+E39 -> 235334.89 | F40: =F27+F33+F39 -> 303280.14 | G40: =G27+G33+G39 -> 372451.43 | H40: =H27+H33+H39 -> 442936.68 | I40: =I27+I33+I39 -> 514830.09 | J40: =J27+J33+J39 -> 588232.64 | K40: =K27+K33+K39 -> 663252.52 | ... AZ40: =AZ27+AZ33+AZ39 -> 8565481.7
B41: Other assets
B45: Other assets total | D45: =subtotal(9,D42:D44) -> 0 | E45: =subtotal(9,E42:E44) -> 0 | F45: =subtotal(9,F42:F44) -> 0 | G45: =subtotal(9,G42:G44) -> 0 | H45: =subtotal(9,H42:H44) -> 0 | I45: =subtotal(9,I42:I44) -> 0 | J45: =subtotal(9,J42:J44) -> 0 | K45: =subtotal(9,K42:K44) -> 0 | ... AZ45: =subtotal(9,AZ42:AZ44) -> 0
B46: Assets Total | D46: =D27+D33+D39+D45 -> 222533.67 | E46: =E27+E33+E39+E45 -> 235334.89 | F46: =F27+F33+F39+F45 -> 303280.14 | G46: =G27+G33+G39+G45 -> 372451.43 | H46: =H27+H33+H39+H45 -> 442936.68 | I46: =I27+I33+I39+I45 -> 514830.09 | J46: =J27+J33+J39+J45 -> 588232.64 | K46: =K27+K33+K39+K45 -> 663252.52 | ... AZ46: =AZ27+AZ33+AZ39+AZ45 -> 8565481.7
B49: Debts | C49: Interest/ growth rates | D49: Baseline June 2025 | E49: 46143 | F49: 46508 | G49: 46874 | H49: 47239 | I49: 47604 | J49: 47969 | K49: 48335 | L49: 48700 | M49: 49065 | N49: 49430 | O49: 49796 | P49: 50161 | Q49: 50526 | R49: 50891 | S49: 51257 | T49: 51622 | U49: 51987 | V49: 52352 | W49: 52718 | X49: 53083 | Y49: 53448 | Z49: 53813 | AA49: 54179 | AB49: 54544 | AC49: 54909 | AD49: 55274 | AE49: 55640 | AF49: 56005 | AG49: 56370 | AH49: 56735 | AI49: 57101 | AJ49: 57466 | AK49: 57831 | AL49: 58196 | AM49: 58562 | AN49: 58927 | AO49: 59292 | AP49: 59657 | AQ49: 60023 | AR49: 60388 | AS49: 60753 | AT49: 61118 | AU49: 61484 | AV49: 61849 | AW49: 62214 | AX49: 62579 | AY49: 62945 | AZ49: 63310
B50: Cash/ savings accounts
B51: ='Input Data'!I47 -> mortgage | C51: ='Input Data'!L47/100 -> 0.0146 | D51: =-'Input Data'!N47 -> -346257 | E51: =if(FV(($C$51/12),12,'Input Data'!$M47,D51)>0,-FV(($C$51/12),12,'Input Data'!$M47,D51),0) -> -324516.82 | F51: =if(FV(($C$51/12),12,'Input Data'!$M47,E51)>0,-FV(($C$51/12),12,'Input Data'!$M47,E51),0) -> -302457.1 | G51: =if(FV(($C$51/12),12,'Input Data'!$M47,F51)>0,-FV(($C$51/12),12,'Input Data'!$M47,F51),0) -> -280073.14 | H51: =if(FV(($C$51/12),12,'Input Data'!$M47,G51)>0,-FV(($C$51/12),12,'Input Data'!$M47,G51),0) -> -257360.18 | I51: =if(FV(($C$51/12),12,'Input Data'!$M47,H51)>0,-FV(($C$51/12),12,'Input Data'!$M47,H51),0) -> -234313.38 | J51: =if(FV(($C$51/12),12,'Input Data'!$M47,I51)>0,-FV(($C$51/12),12,'Input Data'!$M47,I51),0) -> -210927.84 | K51: =if(FV(($C$51/12),12,'Input Data'!$M47,J51)>0,-FV(($C$51/12),12,'Input Data'!$M47,J51),0) -> -187198.58 | L51: =if(FV(($C$51/12),12,'Input Data'!$M47,K51)>0,-FV(($C$51/12),12,'Input Data'!$M47,K51),0) -> -163120.54 | ... AZ51: =if(FV(($C$51/12),12,'Input Data'!$M47,AY51)>0,-FV(($C$51/12),12,'Input Data'!$M47,AY51),0) -> 0
B52: ='Input Data'!I48 | C52: ='Input Data'!L48/100 -> 0 | D52: ='Input Data'!N48 | E52: =if(FV(($C$51/12),12,'Input Data'!$M48,-D52)>0,FV(($C$51/12),12,'Input Data'!$M48,-D52),0) -> 0 | F52: =if(FV(($C$51/12),12,'Input Data'!$M48,-E52)>0,FV(($C$51/12),12,'Input Data'!$M48,-E52),0) -> 0 | G52: =if(FV(($C$51/12),12,'Input Data'!$M48,-F52)>0,FV(($C$51/12),12,'Input Data'!$M48,-F52),0) -> 0 | H52: =if(FV(($C$51/12),12,'Input Data'!$M48,-G52)>0,FV(($C$51/12),12,'Input Data'!$M48,-G52),0) -> 0 | I52: =if(FV(($C$51/12),12,'Input Data'!$M48,-H52)>0,FV(($C$51/12),12,'Input Data'!$M48,-H52),0) -> 0 | J52: =if(FV(($C$51/12),12,'Input Data'!$M48,-I52)>0,FV(($C$51/12),12,'Input Data'!$M48,-I52),0) -> 0 | K52: =if(FV(($C$51/12),12,'Input Data'!$M48,-J52)>0,FV(($C$51/12),12,'Input Data'!$M48,-J52),0) -> 0 | L52: =if(FV(($C$51/12),12,'Input Data'!$M48,-K52)>0,FV(($C$51/12),12,'Input Data'!$M48,-K52),0) -> 0 | ... AZ52: =if(FV(($C$51/12),12,'Input Data'!$M48,-AY52)>0,FV(($C$51/12),12,'Input Data'!$M48,-AY52),0) -> 0
B53: ='Input Data'!I49 | C53: ='Input Data'!L49/100 -> 0 | D53: ='Input Data'!N49 | E53: =if(FV(($C$51/12),12,'Input Data'!$M49,-D53)>0,FV(($C$51/12),12,'Input Data'!$M49,-D53),0) -> 0 | F53: =if(FV(($C$51/12),12,'Input Data'!$M49,-E53)>0,FV(($C$51/12),12,'Input Data'!$M49,-E53),0) -> 0 | G53: =if(FV(($C$51/12),12,'Input Data'!$M49,-F53)>0,FV(($C$51/12),12,'Input Data'!$M49,-F53),0) -> 0 | H53: =if(FV(($C$51/12),12,'Input Data'!$M49,-G53)>0,FV(($C$51/12),12,'Input Data'!$M49,-G53),0) -> 0 | I53: =if(FV(($C$51/12),12,'Input Data'!$M49,-H53)>0,FV(($C$51/12),12,'Input Data'!$M49,-H53),0) -> 0 | J53: =if(FV(($C$51/12),12,'Input Data'!$M49,-I53)>0,FV(($C$51/12),12,'Input Data'!$M49,-I53),0) -> 0 | K53: =if(FV(($C$51/12),12,'Input Data'!$M49,-J53)>0,FV(($C$51/12),12,'Input Data'!$M49,-J53),0) -> 0 | L53: =if(FV(($C$51/12),12,'Input Data'!$M49,-K53)>0,FV(($C$51/12),12,'Input Data'!$M49,-K53),0) -> 0 | ... AZ53: =if(FV(($C$51/12),12,'Input Data'!$M49,-AY53)>0,FV(($C$51/12),12,'Input Data'!$M49,-AY53),0) -> 0
B54: ='Input Data'!I50 | C54: ='Input Data'!L50/100 -> 0 | D54: ='Input Data'!N50 | E54: =if(FV(($C$51/12),12,'Input Data'!$M50,-D54)>0,FV(($C$51/12),12,'Input Data'!$M50,-D54),0) -> 0 | F54: =if(FV(($C$51/12),12,'Input Data'!$M50,-E54)>0,FV(($C$51/12),12,'Input Data'!$M50,-E54),0) -> 0 | G54: =if(FV(($C$51/12),12,'Input Data'!$M50,-F54)>0,FV(($C$51/12),12,'Input Data'!$M50,-F54),0) -> 0 | H54: =if(FV(($C$51/12),12,'Input Data'!$M50,-G54)>0,FV(($C$51/12),12,'Input Data'!$M50,-G54),0) -> 0 | I54: =if(FV(($C$51/12),12,'Input Data'!$M50,-H54)>0,FV(($C$51/12),12,'Input Data'!$M50,-H54),0) -> 0 | J54: =if(FV(($C$51/12),12,'Input Data'!$M50,-I54)>0,FV(($C$51/12),12,'Input Data'!$M50,-I54),0) -> 0 | K54: =if(FV(($C$51/12),12,'Input Data'!$M50,-J54)>0,FV(($C$51/12),12,'Input Data'!$M50,-J54),0) -> 0 | L54: =if(FV(($C$51/12),12,'Input Data'!$M50,-K54)>0,FV(($C$51/12),12,'Input Data'!$M50,-K54),0) -> 0 | ... AZ54: =if(FV(($C$51/12),12,'Input Data'!$M50,-AY54)>0,FV(($C$51/12),12,'Input Data'!$M50,-AY54),0) -> 0
B55: ='Input Data'!I51 | C55: ='Input Data'!L51/100 -> 0 | D55: ='Input Data'!N51 | E55: =if(FV(($C$51/12),12,'Input Data'!$M51,-D55)>0,FV(($C$51/12),12,'Input Data'!$M51,-D55),0) -> 0 | F55: =if(FV(($C$51/12),12,'Input Data'!$M51,-E55)>0,FV(($C$51/12),12,'Input Data'!$M51,-E55),0) -> 0 | G55: =if(FV(($C$51/12),12,'Input Data'!$M51,-F55)>0,FV(($C$51/12),12,'Input Data'!$M51,-F55),0) -> 0 | H55: =if(FV(($C$51/12),12,'Input Data'!$M51,-G55)>0,FV(($C$51/12),12,'Input Data'!$M51,-G55),0) -> 0 | I55: =if(FV(($C$51/12),12,'Input Data'!$M51,-H55)>0,FV(($C$51/12),12,'Input Data'!$M51,-H55),0) -> 0 | J55: =if(FV(($C$51/12),12,'Input Data'!$M51,-I55)>0,FV(($C$51/12),12,'Input Data'!$M51,-I55),0) -> 0 | K55: =if(FV(($C$51/12),12,'Input Data'!$M51,-J55)>0,FV(($C$51/12),12,'Input Data'!$M51,-J55),0) -> 0 | L55: =if(FV(($C$51/12),12,'Input Data'!$M51,-K55)>0,FV(($C$51/12),12,'Input Data'!$M51,-K55),0) -> 0 | ... AZ55: =if(FV(($C$51/12),12,'Input Data'!$M51,-AY55)>0,FV(($C$51/12),12,'Input Data'!$M51,-AY55),0) -> 0
B56: Debts total | D56: =subtotal(9,D51:D55) -> -346257 | E56: =subtotal(9,E51:E55) -> -324516.82 | F56: =subtotal(9,F51:F55) -> -302457.1 | G56: =subtotal(9,G51:G55) -> -280073.14 | H56: =subtotal(9,H51:H55) -> -257360.18 | I56: =subtotal(9,I51:I55) -> -234313.38 | J56: =subtotal(9,J51:J55) -> -210927.84 | K56: =subtotal(9,K51:K55) -> -187198.58 | ... AZ56: =subtotal(9,AZ51:AZ55) -> 0
B58: Net Wealth Total | D58: =D46+D56 -> -123723.33 | E58: =E46+E56 -> -89181.923 | F58: =F46+F56 -> 823.04387 | G58: =G46+G56 -> 92378.294 | H58: =H46+H56 -> 185576.5 | I58: =I46+I56 -> 280516.71 | J58: =J46+J56 -> 377304.8 | K58: =K46+K56 -> 476053.94 | ... AZ58: =AZ46+AZ56 -> 8565481.7
B62: Net wealth impact summary | C62: ="1 year ("&(Year(today())+1)&")" -> 1 year (2026) | D62: ="5 years ("&(Year(today())+5)&")" -> 5 years (2030) | E62: ="10 years ("&(Year(today())+10)&")" -> 10 years (2035) | F62: ="20 years ("&(Year(today())+20)&")" -> 20 years (2045)
B63: Projected Value | C63: =E58 -> -89181.923 | D63: =I58 -> 280516.71 | E63: =N58 -> 785320.42 | F63: =X58 -> 1851826.4
B64: ="Delta from "&Right(D49,10) -> Delta from June 2025 | C64: =C63-$D$58 -> 34541.407 | D64: =D63-$D$58 -> 404240.04 | E64: =E63-$D$58 -> 909043.75 | F64: =F63-$D$58 -> 1975549.8
B65: % | C65: =C64/$C$63 -> -0.38731399 | D65: =D64/$D$63 -> 1.4410551 | E65: =E64/$E$63 -> 1.157545 | F65: =F64/$F$63 -> 1.0668115
B70: Meet Financial Goal: Mortgage
B72: Assumptions | C72: Property is bought on fixed-interest mortgage, capital gains are considered in growth rate of asset but rental income is not (this will be considered in lever B)
B74: Goal Number
B76: Type of lever | C76: Independent
B77: Net income impact | C77: N
B78: Capital gains impact | C78: Y
B81: Mortgage details
B82: Year of purchase | C82: {=INDEX('Input Data'!D11:D13, A74)} -> #REF!
B83: Amount Needed | C83: {=INDEX('Input Data'!E11:E13, A74)-INDEX('Input Data'!I11:I13, A74)} -> #VALUE! | D83: GBP
B84: Length of mortgage | C84: {=INDEX('Input Data'!G11:G13, A74)} -> #REF! | D84: Years
B85: Down deposit | C85: 0.5
B86: Long-term annual mortgage interest rate (GBP) | C86: 5.34% | F86: Source: | G86: https://www.nerdwallet.com/uk/mortgages/mortgage-rates/
B87: Long-term monthly mortgage interest rate (GBP) | C87: =C86/12 -> 0.00445
B89: Loan amount | C89: {=INDEX('Input Data'!E11:E13, A74)} -> #REF! | D89: GBP
B90: Monthly interest repayment | C90: =rig_mor_la*(rig_mor_mo_ir*(1+rig_mor_mo_ir)^(C84*12))/((1+rig_mor_mo_ir)^(C84*12)-1) -> #NAME? | D90: GBP
B91: Annual interest repayment | C91: =rig_mor_mo_pay*12 -> #NAME? | D91: GBP
B94: Annual property value increase in London | F94: Source: | G94: https://www.nerdwallet.com/uk/mortgages/house-prices/
B96: Net income impact by year
D97: Baseline (June 2025) | E97: 46143 | F97: 46508 | G97: 46874 | H97: 47239 | I97: 47604 | J97: 47969 | K97: 48335 | L97: 48700 | M97: 49065 | N97: 49430 | O97: 49796 | P97: 50161 | Q97: 50526 | R97: 50891 | S97: 51257 | T97: 51622 | U97: 51987 | V97: 52352 | W97: 52718 | X97: 53083 | Y97: 53448 | Z97: 53813 | AA97: 54179 | AB97: 54544 | AC97: 54909 | AD97: 55274 | AE97: 55640 | AF97: 56005 | AG97: 56370 | AH97: 56735 | AI97: 57101 | AJ97: 57466 | AK97: 57831 | AL97: 58196 | AM97: 58562 | AN97: 58927 | AO97: 59292 | AP97: 59657 | AQ97: 60023 | AR97: 60388 | AS97: 60753 | AT97: 61118 | AU97: 61484 | AV97: 61849 | AW97: 62214 | AX97: 62579 | AY97: 62945 | AZ97: 63310
B98: Mortgage payments | E98: =-rig_mor_la-rig_mor_ann_pay -> #NAME? | F98: =-rig_mor_ann_pay -> #NAME? | G98: =-rig_mor_ann_pay -> #NAME? | H98: =-rig_mor_ann_pay -> #NAME? | I98: =-rig_mor_ann_pay -> #NAME? | J98: =-rig_mor_ann_pay -> #NAME? | K98: =-rig_mor_ann_pay -> #NAME? | L98: =-rig_mor_ann_pay -> #NAME? | M98: =-rig_mor_ann_pay -> #NAME? | ... AD98: =-rig_mor_ann_pay -> #NAME?
B99: 2. London property annual net income impact | D99: =D98 | E99: =E98 -> #NAME? | F99: =F98 -> #NAME? | G99: =G98 -> #NAME? | H99: =H98 -> #NAME? | I99: =I98 -> #NAME? | J99: =J98 -> #NAME? | K99: =K98 -> #NAME? | ... AL99: =AL98 | AZ99: =AZ98
B102: Cumulative net wealth impact
D103: Baseline (June 2025) | E103: 46143 | F103: 46508 | G103: 46874 | H103: 47239 | I103: 47604 | J103: 47969 | K103: 48335 | L103: 48700 | M103: 49065 | N103: 49430 | O103: 49796 | P103: 50161 | Q103: 50526 | R103: 50891 | S103: 51257 | T103: 51622 | U103: 51987 | V103: 52352 | W103: 52718 | X103: 53083 | Y103: 53448 | Z103: 53813 | AA103: 54179 | AB103: 54544 | AC103: 54909 | AD103: 55274 | AE103: 55640 | AF103: 56005 | AG103: 56370 | AH103: 56735 | AI103: 57101 | AJ103: 57466 | AK103: 57831 | AL103: 58196 | AM103: 58562 | AN103: 58927 | AO103: 59292 | AP103: 59657 | AQ103: 60023 | AR103: 60388 | AS103: 60753 | AT103: 61118 | AU103: 61484 | AV103: 61849 | AW103: 62214 | AX103: 62579 | AY103: 62945 | AZ103: 63310
B104: Loan value (inc down deposit) | E104: =-E105 -> #VALUE! | F104: =-fv($C86,(year(F103)-year($E103)),$C91,$E104) -> #NAME? | G104: =-fv($C86,(year(G103)-year($E103)),$C91,$E104) -> #NAME? | H104: =-fv($C86,(year(H103)-year($E103)),$C91,$E104) -> #NAME? | I104: =-fv($C86,(year(I103)-year($E103)),$C91,$E104) -> #NAME? | J104: =-fv($C86,(year(J103)-year($E103)),$C91,$E104) -> #NAME? | K104: =-fv($C86,(year(K103)-year($E103)),$C91,$E104) -> #NAME? | L104: =-fv($C86,(year(L103)-year($E103)),$C91,$E104) -> #NAME? | M104: =-fv($C86,(year(M103)-year($E103)),$C91,$E104) -> #NAME? | ... AD104: =-fv($C86,(year(AD103)-year($E103)),$C91,$E104) -> #NAME?
B105: Gross apartment value | E105: =C83 -> #VALUE! | F105: =E105*(1+rig_apt_ann_gro) -> #VALUE! | G105: =F105*(1+rig_apt_ann_gro) -> #VALUE! | H105: =G105*(1+rig_apt_ann_gro) -> #VALUE! | I105: =H105*(1+rig_apt_ann_gro) -> #VALUE! | J105: =I105*(1+rig_apt_ann_gro) -> #VALUE! | K105: =J105*(1+rig_apt_ann_gro) -> #VALUE! | L105: =K105*(1+rig_apt_ann_gro) -> #VALUE! | M105: =L105*(1+rig_apt_ann_gro) -> #VALUE! | ... AZ105: =AY105*(1+rig_apt_ann_gro) -> #VALUE!
B106: 2. London property annual net wealth impact (inclusive of the one-time payment from sister) | E106: =sum(E104:E105) -> #VALUE! | F106: =sum(F104:F105) -> #NAME? | G106: =sum(G104:G105) -> #NAME? | H106: =sum(H104:H105) -> #NAME? | I106: =sum(I104:I105) -> #NAME? | J106: =sum(J104:J105) -> #NAME? | K106: =sum(K104:K105) -> #NAME? | L106: =sum(L104:L105) -> #NAME? | ... AZ106: =sum(AZ104:AZ105) -> #VALUE!
B109: Net wealth impact summary
D110: Delta from 0. Do Nothing
D111: abs | E111: %
B112: 1 year (2026) | D112: =E106 -> #VALUE! | E112: =D112/$C$39 -> #VALUE!
B113: 5 years (2030) | D113: =I106 -> #NAME? | E113: =D113/$C$46 -> #NAME?
B114: 10 years (2035) | D114: =N106 -> #NAME? | E114: =D114/$C$47 -> #NAME?
B115: 20 years (2045) | D115: =X106 -> #NAME? | E115: =D115/$H$62 -> #NAME?
A119: 1 | B119: Meet Financial Goal: Purchasing NE London Property
B121: Assumptions | C121: Family provides money for downpayment
C122: Interest rate remains constant, payments are standardized (no large one-off payments included in the calculation), assuming no cap in net income reductions from debt payments
B124: Type of lever | C124: Independent
B125: Net income impact | C125: Y
B126: Capital gains impact | C126: N
B127: Net Worth Impact | C127: N
B130: Down payment | C130: 200000
B131: Outstanding Mortgage Value | C131: 400000
B132: Timeline (years) | C132: 25
B133: Long-term annual interest rate (GBP) | C133: ='Input Data'!F49 -> 0.0424
B134: Long-term monthly interest rate (GBP) calculated | C134: =C133/12 -> 0.0035333333
B135: Annual Payments | C135: =12*C136 -> 25976.56
B136: Monthly Payments | C136: =PMT(C134,12*C132,-C131,0,) -> 2164.7133
B140: Net income impact by year
C142: Asset Appreciation | D142: Baseline June 2025 | E142: 46143 | F142: 46508 | G142: 46874 | H142: 47239 | I142: 47604 | J142: 47969 | K142: 48335 | L142: 48700 | M142: 49065 | N142: 49430 | O142: 49796 | P142: 50161 | Q142: 50526 | R142: 50891 | S142: 51257 | T142: 51622 | U142: 51987 | V142: 52352 | W142: 52718 | X142: 53083 | Y142: 53448 | Z142: 53813 | AA142: 54179 | AB142: 54544 | AC142: 54909 | AD142: 55274 | AE142: 55640 | AF142: 56005 | AG142: 56370 | AH142: 56735 | AI142: 57101 | AJ142: 57466 | AK142: 57831 | AL142: 58196 | AM142: 58562 | AN142: 58927 | AO142: 59292 | AP142: 59657 | AQ142: 60023 | AR142: 60388 | AS142: 60753 | AT142: 61118 | AU142: 61484 | AV142: 61849 | AW142: 62214 | AX142: 62579 | AY142: 62945 | AZ142: 63310
B143: 50% Property Value | C143: ='Input Data'!F52 -> 0.033 | D143: ='Input Data'!F56/2 -> 600000 | E143: =D143*(1+$C143) -> 619800 | F143: =E143*(1+$C143) -> 640253.4 | G143: =F143*(1+$C143) -> 661381.76 | H143: =G143*(1+$C143) -> 683207.36 | I143: =H143*(1+$C143) -> 705753.2 | J143: =I143*(1+$C143) -> 729043.06 | K143: =J143*(1+$C143) -> 753101.48 | L143: =K143*(1+$C143) -> 777953.83 | ... AZ143: =AY143*(1+$C143) -> 2850799.6
...

Sheet Summary
B1: Net income trajectory
C3: =Model!E9 -> 46143 | D3: =Model!F9 -> 46508 | E3: =Model!G9 -> 46874 | F3: =Model!H9 -> 47239 | G3: =Model!I9 -> 47604 | H3: =Model!J9 -> 47969 | I3: =Model!K9 -> 48335 | J3: =Model!L9 -> 48700 | ... AX3: =Model!AZ9 -> 63310
B4: Do-Nothing (Baseline) | C4: =Model!E14 -> 50845.56 | D4: =Model!F14 -> 50845.56 | E4: =Model!G14 -> 50845.56 | F4: =Model!H14 -> 50845.56 | G4: =Model!I14 -> 50845.56 | H4: =Model!J14 -> 50845.56 | I4: =Model!K14 -> 50845.56 | J4: =Model!L14 -> 50845.56 | ... AX4: =Model!AZ14 -> 50845.56
B5: =Model!B119 -> Meet Financial Goal: Purchasing NE London Property | C5: =Model!E149 -> -33976.56 | D5: =Model!F149 -> -33976.56 | E5: =Model!G149 -> -33976.56 | F5: =Model!H149 -> -33976.56 | G5: =Model!I149 -> -33976.56 | H5: =Model!J149 -> -33976.56 | I5: =Model!K149 -> -33976.56 | J5: =Model!L149 -> -33976.56 | ... AX5: =Model!AZ149 -> 0
B6: =Model!B167 -> Meet Financial Goal: Short Term Expenses | C6: =Model!E190 -> 0 | D6: =Model!F190 -> 0 | E6: =Model!G190 -> 0 | F6: =Model!H190 -> 0 | G6: =Model!I190 -> 0 | H6: =Model!J190 -> 0 | I6: =Model!K190 -> 0 | J6: =Model!L190 -> 0 | ... AX6: =Model!AZ190 -> 0
B7: =Model!B204 -> Meet Financial Goal: Comfortable Retirement | C7: =Model!E229 -> -15315.395 | D7: =Model!F229 -> -15315.395 | E7: =Model!G229 -> -15315.395 | F7: =Model!H229 -> -15315.395 | G7: =Model!I229 -> -15315.395 | H7: =Model!J229 -> -15315.395 | I7: =Model!K229 -> -15315.395 | J7: =Model!L229 -> -15315.395 | ... AX7: =Model!AZ229 -> 50000
B8: Meeting goals cash flow | C8: =sum(C4:C7) -> 1553.6052 | D8: =sum(D4:D7) -> 1553.6052 | E8: =sum(E4:E7) -> 1553.6052 | F8: =sum(F4:F7) -> 1553.6052 | G8: =sum(G4:G7) -> 1553.6052 | H8: =sum(H4:H7) -> 1553.6052 | I8: =sum(I4:I7) -> 1553.6052 | J8: =sum(J4:J7) -> 1553.6052 | ... AX8: =sum(AX4:AX7) -> 100845.56
B9: A. Increasing Salary | C9: =Model!E261 -> 2160 | D9: =Model!F261 -> 2203.2 | E9: =Model!G261 -> 2247.264 | F9: =Model!H261 -> 2292.2093 | G9: =Model!I261 -> 2338.0535 | H9: =Model!J261 -> 2384.8145 | I9: =Model!K261 -> 2432.5108 | J9: =Model!L261 -> 2481.161 | ... AX9: =Model!AZ261 -> 0
B10: B. Side hustles and additional income streams | C10: =Model!E291 -> 0 | D10: =Model!F291 -> 0 | E10: =Model!G291 -> 0 | F10: =Model!H291 -> 0 | G10: =Model!I291 -> 0 | H10: =Model!J291 -> 0 | I10: =Model!K291 -> 0 | J10: =Model!L291 -> 0 | ... AX10: =Model!AZ291 -> 0
B11: C. Reducing Fixed Expenses | C11: =Model!E325 -> 2070 | D11: =Model!F325 -> 2070 | E11: =Model!G325 -> 2070 | F11: =Model!H325 -> 2070 | G11: =Model!I325 -> 2070 | H11: =Model!J325 -> 2070 | I11: =Model!K325 -> 2070 | J11: =Model!L325 -> 2070 | ... AX11: =Model!AZ325 -> 2070
B12: Independent levers cash flow | C12: =SUBTOTAL(9, C9:C11) -> 4230 | D12: =SUBTOTAL(9, D9:D11) -> 4273.2 | E12: =SUBTOTAL(9, E9:E11) -> 4317.264 | F12: =SUBTOTAL(9, F9:F11) -> 4362.2093 | G12: =SUBTOTAL(9, G9:G11) -> 4408.0535 | H12: =SUBTOTAL(9, H9:H11) -> 4454.8145 | I12: =SUBTOTAL(9, I9:I11) -> 4502.5108 | J12: =SUBTOTAL(9, J9:J11) -> 4551.161 | ... AX12: =SUBTOTAL(9, AX9:AX11) -> 2070
B13: Cash flow after independent levers | C13: =SUM(C8:C11) -> 5783.6052 | D13: =SUM(D8:D11) -> 5826.8052 | E13: =SUM(E8:E11) -> 5870.8692 | F13: =SUM(F8:F11) -> 5915.8145 | G13: =SUM(G8:G11) -> 5961.6587 | H13: =SUM(H8:H11) -> 6008.4198 | I13: =SUM(I8:I11) -> 6056.1161 | J13: =SUM(J8:J11) -> 6104.7663 | ... AX13: =SUM(AX8:AX11) -> 102915.56
B14: D. Investing in higher-yield savings | C14: 0 | D14: 0 | E14: 0 | F14: 0 | G14: 0 | H14: 0 | I14: 0 | J14: 0 | K14: 0 | L14: 0 | M14: 0 | N14: 0 | O14: 0 | P14: 0 | Q14: 0 | R14: 0 | S14: 0 | T14: 0 | U14: 0 | V14: 0 | W14: 0 | X14: 0 | Y14: 0 | Z14: 0 | AA14: 0 | AB14: 0 | AC14: 0 | AD14: 0 | AE14: 0 | AF14: 0 | AG14: 0 | AH14: 0 | AI14: 0 | AJ14: 0 | AK14: 0 | AL14: 0 | AM14: 0 | AN14: 0 | AO14: 0 | AP14: 0 | AQ14: 0 | AR14: 0 | AS14: 0 | AT14: 0 | AU14: 0 | AV14: 0 | AW14: 0 | AX14: 0
B15: E. Private pension contributions | C15: =Model!E404 -> 0 | D15: =Model!F404 -> 0 | E15: =Model!G404 -> 0 | F15: =Model!H404 -> 0 | G15: =Model!I404 -> 0 | H15: =Model!J404 -> 0 | I15: =Model!K404 -> 0 | J15: =Model!L404 -> 0 | ... AX15: =Model!AZ404 -> 0
B16: F.i. Starting to invest/ investing more - lump sum | C16: =Model!E438 -> 0 | D16: =Model!F438 -> 0 | E16: =Model!G438 -> 0 | F16: =Model!H438 -> 0 | G16: =Model!I438 -> 0 | H16: =Model!J438 -> 0 | I16: =Model!K438 -> 0 | J16: =Model!L438 -> 0 | ... AX16: =Model!AZ438 -> 0
B17: F.ii. Starting to invest/ investing more - ongoing | C17: =Model!E482 -> 21.129031 | D17: =Model!F482 -> 42.258063 | E17: =Model!G482 -> 63.387094 | F17: =Model!H482 -> 84.516126 | G17: =Model!I482 -> 105.64516 | H17: =Model!J482 -> 126.77419 | I17: =Model!K482 -> 147.90322 | J17: =Model!L482 -> 169.03225 | ... AX17: =Model!AZ482 -> 7035.0968
B18: G.i. Adjust investments - lump | C18: =Model!E526 -> 498.22256 | D18: =Model!F526 -> 634.10649 | E18: =Model!G526 -> 791.65251 | F18: =Model!H526 -> 973.83216 | G18: =Model!I526 -> 1183.9989 | H18: =Model!J526 -> 1425.9353 | I18: =Model!K526 -> 1703.9068 | J18: =Model!L526 -> 2022.721 | ... AX18: =Model!AZ526 -> 375734.17
B19: G.ii. Adjust investments - continuous | C19: =Model!E560 -> 122.76435 | D19: =Model!F560 -> 203.42829 | E19: =Model!G560 -> 299.32482 | F19: =Model!H560 -> 412.50708 | G19: =Model!I560 -> 545.27316 | H19: =Model!J560 -> 700.19356 | I19: =Model!K560 -> 880.14174 | J19: =Model!L560 -> 1088.3279 | ... AX19: =Model!AZ560 -> 209340.68
B20: H. Emergency Fund/Child Savings | C20: =Model!E601 -> -1553.6052 | D20: =Model!F601 -> -1553.6052 | E20: =Model!G601 -> -1553.6052 | F20: =Model!H601 -> -1553.6052 | G20: =Model!I601 -> -1553.6052 | H20: =Model!J601 -> -1553.6052 | I20: =Model!K601 -> -1553.6052 | J20: =Model!L601 -> -1553.6052 | ... AX20: =Model!AZ601 -> -1553.6052
B21: F & G levers combined | C21: =sum(C16:C19) -> 642.11594 | D21: =sum(D16:D19) -> 879.79284 | E21: =sum(E16:E19) -> 1154.3644 | F21: =sum(F16:F19) -> 1470.8554 | G21: =sum(G16:G19) -> 1834.9172 | H21: =sum(H16:H19) -> 2252.9031 | I21: =sum(I16:I19) -> 2731.9518 | J21: =sum(J16:J19) -> 3280.0811 | ... AX21: =sum(AX16:AX19) -> 592109.95
B22: Cash flow after dependent levers | C22: =C8+sum(C14:C20) -> 642.11594 | D22: =D8+sum(D14:D20) -> 879.79284 | E22: =E8+sum(E14:E20) -> 1154.3644 | F22: =F8+sum(F14:F20) -> 1470.8554 | G22: =G8+sum(G14:G20) -> 1834.9172 | H22: =H8+sum(H14:H20) -> 2252.9031 | I22: =I8+sum(I14:I20) -> 2731.9518 | J22: =J8+sum(J14:J20) -> 3280.0811 | ... AX22: =AX8+sum(AX14:AX20) -> 691401.9
B23: I. Refinancing High-Interest Debt | C23: N/A | D23: N/A | E23: N/A | F23: N/A | G23: N/A | H23: N/A | I23: N/A | J23: N/A | K23: N/A | L23: N/A | M23: N/A | N23: N/A | O23: N/A | P23: N/A | Q23: N/A | R23: N/A | S23: N/A | T23: N/A | U23: N/A | V23: N/A | W23: N/A | X23: N/A | Y23: N/A | Z23: N/A | AA23: N/A | AB23: N/A | AC23: N/A | AD23: N/A | AE23: N/A | AF23: N/A | AG23: N/A | AH23: N/A | AI23: N/A | AJ23: N/A | AK23: N/A | AL23: N/A | AM23: N/A | AN23: N/A | AO23: N/A | AP23: N/A | AQ23: N/A | AR23: N/A | AS23: N/A | AT23: N/A | AU23: N/A | AV23: N/A | AW23: N/A | AX23: N/A
B24: J. Consolidating or Paying Off Debt Faster | C24: N/A | D24: N/A | E24: N/A | F24: N/A | G24: N/A | H24: N/A | I24: N/A | J24: N/A | K24: N/A | L24: N/A | M24: N/A | N24: N/A | O24: N/A | P24: N/A | Q24: N/A | R24: N/A | S24: N/A | T24: N/A | U24: N/A | V24: N/A | W24: N/A | X24: N/A | Y24: N/A | Z24: N/A | AA24: N/A | AB24: N/A | AC24: N/A | AD24: N/A | AE24: N/A | AF24: N/A | AG24: N/A | AH24: N/A | AI24: N/A | AJ24: N/A | AK24: N/A | AL24: N/A | AM24: N/A | AN24: N/A | AO24: N/A | AP24: N/A | AQ24: N/A | AR24: N/A | AS24: N/A | AT24: N/A | AU24: N/A | AV24: N/A | AW24: N/A | AX24: N/A
B28: Net wealth trajectory
C30: =C3 -> 46143 | D30: =D3 -> 46508 | E30: =E3 -> 46874 | F30: =F3 -> 47239 | G30: =G3 -> 47604 | H30: =H3 -> 47969 | I30: =I3 -> 48335 | J30: =J3 -> 48700 | ... AX30: =AX3 -> 63310
B31: 0. Do-Nothing (Baseline) | C31: =Model!E58 -> -89181.923 | D31: =Model!F58 -> 823.04387 | E31: =Model!G58 -> 92378.294 | F31: =Model!H58 -> 185576.5 | G31: =Model!I58 -> 280516.71 | H31: =Model!J58 -> 377304.8 | I31: =Model!K58 -> 476053.94 | J31: =Model!L58 -> 576885.16 | ... AX31: =Model!AZ58 -> 8565481.7
B32: =Model!B119 -> Meet Financial Goal: Purchasing NE London Property | C32: =Model!E153 -> -22959.258 | D32: =Model!F153 -> -18891.07 | E32: =Model!G153 -> -13733.251 | F32: =Model!H153 -> -7445.5981 | G32: =Model!I153 -> 13.600143 | H32: =Model!J153 -> 8687.6231 | I32: =Model!K153 -> 18621.378 | J32: =Model!L153 -> 29861.463 | ... AX32: =Model!AZ153 -> 2001385.6
B33: =Model!B167 -> Meet Financial Goal: Short Term Expenses | C33: =Model!E191 -> -15800 | D33: =Model!F191 -> -15800 | E33: =Model!G191 -> -15800 | F33: =Model!H191 -> -15800 | G33: =Model!I191 -> -15800 | H33: =Model!J191 -> -15800 | I33: =Model!K191 -> -15800 | J33: =Model!L191 -> -15800 | ... AX33: =Model!AZ191 -> -15800
B34: =Model!B204 -> Meet Financial Goal: Comfortable Retirement | C34: =Model!E230 -> 459.46185 | D34: =Model!F230 -> 16707.565 | E34: =Model!G230 -> 33443.11 | F34: =Model!H230 -> 50680.722 | G34: =Model!I230 -> 68435.463 | H34: =Model!J230 -> 86722.846 | I34: =Model!K230 -> 105558.85 | J34: =Model!L230 -> 124959.93 | ... AX34: =Model!AZ230 -> 692260.75
B35: Meeting goals net wealth | C35: =sum(C31:C34) -> -127481.72 | D35: =sum(D31:D34) -> -17160.462 | E35: =sum(E31:E34) -> 96288.154 | F35: =sum(F31:F34) -> 213011.63 | G35: =sum(G31:G34) -> 333165.77 | H35: =sum(H31:H34) -> 456915.27 | I35: =sum(I31:I34) -> 584434.17 | J35: =sum(J31:J34) -> 715906.55 | ... AX35: =sum(AX31:AX34) -> 11243328
B36: A. Increasing Salary | C36: =Model!E267 -> 2160 | D36: =Model!F267 -> 4363.2 | E36: =Model!G267 -> 6610.464 | F36: =Model!H267 -> 8902.6733 | G36: =Model!I267 -> 11240.727 | H36: =Model!J267 -> 13625.541 | I36: =Model!K267 -> 16058.052 | J36: =Model!L267 -> 18539.213 | ... AX36: =Model!AZ267 -> 0
B37: B. Side hustles and additional income streams | C37: =0 -> 0 | D37: =0 -> 0 | E37: =0 -> 0 | F37: =0 -> 0 | G37: =0 -> 0 | H37: =0 -> 0 | I37: =0 -> 0 | J37: =0 -> 0 | ... AX37: =0 -> 0
B38: C. Reducing Fixed Expenses | C38: =Model!E330 -> 2070 | D38: =Model!F330 -> 4140 | E38: =Model!G330 -> 6210 | F38: =Model!H330 -> 8280 | G38: =Model!I330 -> 10350 | H38: =Model!J330 -> 12420 | I38: =Model!K330 -> 14490 | J38: =Model!L330 -> 16560 | ... AX38: =Model!AZ330 -> 99360
B39: Independent levers net wealth | C39: =sum(C35:C38) -> -123251.72 | D39: =sum(D35:D38) -> -8657.262 | E39: =sum(E35:E38) -> 109108.62 | F39: =sum(F35:F38) -> 230194.3 | G39: =sum(G35:G38) -> 354756.5 | H39: =sum(H35:H38) -> 482960.81 | I39: =sum(I35:I38) -> 614982.22 | J39: =sum(J35:J38) -> 751005.77 | ... AX39: =sum(AX35:AX38) -> 11342688
B40: D. Higher-yield savings | C40: =Model!E359 -> 0 | D40: =Model!F359 -> 54.376184 | E40: =Model!G359 -> 165.03172 | F40: =Model!H359 -> 333.93638 | G40: =Model!I359 -> 563.12889 | H40: =Model!J359 -> 854.71932 | I40: =Model!K359 -> 1210.8916 | J40: =Model!L359 -> 1633.9061 | ... AX40: =Model!AZ359 -> 736507.71
B41: E. Private pension contributions | C41: =Model!E405 -> 0 | D41: =Model!F405 -> 0 | E41: =Model!G405 -> 0 | F41: =Model!H405 -> 0 | G41: =Model!I405 -> 0 | H41: =Model!J405 -> 0 | I41: =Model!K405 -> 0 | J41: =Model!L405 -> 0 | ... AX41: =Model!AZ405 -> 0
B42: F.i. Investing - lump sum | C42: =Model!E446 -> 0 | D42: =Model!F446 -> 0 | E42: =Model!G446 -> 0 | F42: =Model!H446 -> 0 | G42: =Model!I446 -> 0 | H42: =Model!J446 -> 0 | I42: =Model!K446 -> 0 | J42: =Model!L446 -> 0 | ... AX42: =Model!AZ446 -> 0
B43: F.ii. Investing - ongoing | C43: =Model!E491 -> 21.129031 | D43: =Model!F491 -> 174.78059 | E43: =Model!G491 -> 468.94159 | F43: =Model!H491 -> 912.17161 | G43: =Model!I491 -> 1513.6439 | H43: =Model!J491 -> 2283.1896 | I43: =Model!K491 -> 3231.3445 | J43: =Model!L491 -> 4369.4 | ... AX43: =Model!AZ491 -> 1261179.5
B44: G.i. Adjust investments - lump | C44: =Model!E537 -> 3831.3426 | D44: =Model!F537 -> 9995.8862 | E44: =Model!G537 -> 17303.318 | F44: =Model!H537 -> 25918.989 | G44: =Model!I537 -> 36030.032 | H44: =Model!J537 -> 47848.102 | I44: =Model!K537 -> 61612.459 | J44: =Model!L537 -> 77593.424 | ... AX44: =Model!AZ537 -> 21434691
B45: G.ii. Adjust investments - continuous | C45: =Model!E571 -> 572.76435 | D45: =Model!F571 -> 1631.4583 | E45: =Model!G571 -> 3321.6939 | F45: =Model!H571 -> 5745.2605 | G45: =Model!I571 -> 9016.9929 | H45: =Model!J571 -> 13266.29 | I45: =Model!K571 -> 18638.806 | J45: =Model!L571 -> 25298.32 | ... AX45: =Model!AZ571 -> 11023278
B46: H. Emergency Fund/Child Savings | C46: =Model!E607 -> 0 | D46: =Model!F607 -> 54.376184 | E46: =Model!G607 -> 165.03172 | F46: =Model!H607 -> 333.93638 | G46: =Model!I607 -> 563.12889 | H46: =Model!J607 -> 854.71932 | I46: =Model!K607 -> 1210.8916 | J46: =Model!L607 -> 1633.9061 | ... AX46: =Model!AZ607 -> 112462.78
B47: F & G levers combined | C47: =sum(C42:C45) -> 4425.2359 | D47: =sum(D42:D45) -> 11802.125 | E47: =sum(E42:E45) -> 21093.954 | F47: =sum(F42:F45) -> 32576.422 | G47: =sum(G42:G45) -> 46560.669 | H47: =sum(H42:H45) -> 63397.582 | I47: =sum(I42:I45) -> 83482.61 | J47: =sum(J42:J45) -> 107261.14 | ... AX47: =sum(AX42:AX45) -> 33719148
B48: I. Refinancing High-Interest Debt | C48: N/A | D48: N/A | E48: N/A | F48: N/A | G48: N/A | H48: N/A | I48: N/A | J48: N/A | K48: N/A | L48: N/A | M48: N/A | N48: N/A | O48: N/A | P48: N/A | Q48: N/A | R48: N/A | S48: N/A | T48: N/A | U48: N/A | V48: N/A | W48: N/A | X48: N/A | Y48: N/A | Z48: N/A | AA48: N/A | AB48: N/A | AC48: N/A | AD48: N/A | AE48: N/A | AF48: N/A | AG48: N/A | AH48: N/A | AI48: N/A | AJ48: N/A | AK48: N/A | AL48: N/A | AM48: N/A | AN48: N/A | AO48: N/A | AP48: N/A | AQ48: N/A | AR48: N/A | AS48: N/A | AT48: N/A | AU48: N/A | AV48: N/A | AW48: N/A | AX48: N/A
B49: J. Consolidating or Paying Off Debt Faster | C49: N/A | D49: N/A | E49: N/A | F49: N/A | G49: N/A | H49: N/A | I49: N/A | J49: N/A | K49: N/A | L49: N/A | M49: N/A | N49: N/A | O49: N/A | P49: N/A | Q49: N/A | R49: N/A | S49: N/A | T49: N/A | U49: N/A | V49: N/A | W49: N/A | X49: N/A | Y49: N/A | Z49: N/A | AA49: N/A | AB49: N/A | AC49: N/A | AD49: N/A | AE49: N/A | AF49: N/A | AG49: N/A | AH49: N/A | AI49: N/A | AJ49: N/A | AK49: N/A | AL49: N/A | AM49: N/A | AN49: N/A | AO49: N/A | AP49: N/A | AQ49: N/A | AR49: N/A | AS49: N/A | AT49: N/A | AU49: N/A | AV49: N/A | AW49: N/A | AX49: N/A
B52: Net income deltas/ impact from Do-Nothing
C54: 1 Year | E54: 5 Year | G54: 10 Year | I54: 20 Year
C55: abs | D55: % | E55: abs | F55: % | G55: abs | H55: % | I55: abs | J55: %
B56: 0. Do-Nothing (Baseline) | C56: =C4 -> 50845.56 | E56: =G4 -> 50845.56 | G56: =L4 -> 50845.56 | I56: =V4 -> 50845.56
B57: =Model!B119 -> Meet Financial Goal: Purchasing NE London Property | C57: =C5 -> -33976.56 | D57: =C57/$C$56 -> -0.66823061 | E57: =G5 -> -33976.56 | F57: =E57/$E$56 -> -0.66823061 | G57: =L5 -> -33976.56 | H57: =G57/$G$56 -> -0.66823061 | I57: =V5 -> -33976.56 | J57: =I57/$I$56 -> -0.66823061
B58: =Model!B167 -> Meet Financial Goal: Short Term Expenses | C58: =C6 -> 0 | D58: =C58/$C$56 -> 0 | E58: =G6 -> 0 | F58: =E58/$E$56 -> 0 | G58: =L6 -> 0 | H58: =G58/$G$56 -> 0 | I58: =V6 -> 0 | J58: =I58/$I$56 -> 0
B59: =Model!B204 -> Meet Financial Goal: Comfortable Retirement | C59: =C7 -> -15315.395 | D59: =C59/$C$56 -> -0.30121401 | E59: =G7 -> -15315.395 | F59: =E59/$E$56 -> -0.30121401 | G59: =L7 -> -15315.395 | H59: =G59/$G$56 -> -0.30121401 | I59: =V7 -> -15315.395 | J59: =I59/$I$56 -> -0.30121401
B60: Meeting goals cash flow impact | C60: =sum(C57:C59) -> -49291.955 | D60: =C60/$C$56 -> -0.96944462 | E60: =sum(E57:E59) -> -49291.955 | F60: =E60/$E$56 -> -0.96944462 | G60: =sum(G57:G59) -> -49291.955 | H60: =G60/$G$56 -> -0.96944462 | I60: =sum(I57:I59) -> -49291.955 | J60: =I60/$I$56 -> -0.96944462
B61: A. Increasing Salary | C61: =C9 -> 2160 | D61: =C61/$C$56 -> 0.042481585 | E61: =G9 -> 2338.0535 | F61: =E61/$E$56 -> 0.045983434 | G61: =I9 -> 2432.5108 | H61: =G61/$G$56 -> 0.047841165 | I61: =V9 -> 3146.7121 | J61: =I61/$I$56 -> 0.061887648
B62: B. Side hustles and additional income streams | C62: =C10 -> 0 | D62: =C62/$C$56 -> 0 | E62: =G10 -> 0 | F62: =E62/$E$56 -> 0 | G62: =I10 -> 0 | H62: =G62/$G$56 -> 0 | I62: =V10 -> 0 | J62: =I62/$I$56 -> 0
B63: C. Reducing Fixed Expenses | C63: =C11 -> 2070 | D63: =C63/$C$56 -> 0.040711519 | E63: =G11 -> 2070 | F63: =E63/$E$56 -> 0.040711519 | G63: =I11 -> 2070 | H63: =G63/$G$56 -> 0.040711519 | I63: =V11 -> 2070 | J63: =I63/$I$56 -> 0.040711519
B64: Independent levers cash flow impact | C64: =sum(C61:C63) -> 4230 | D64: =C64/$C$56 -> 0.083193105 | E64: =sum(E61:E63) -> 4408.0535 | F64: =E64/$E$56 -> 0.086694954 | G64: =sum(G61:G63) -> 4502.5108 | H64: =G64/$G$56 -> 0.088552684 | I64: =sum(I61:I63) -> 5216.7121 | J64: =I64/$I$56 -> 0.10259917
B65: D. Higher-yield savings | C65: =C14 -> 0 | D65: =C65/$C$56 -> 0 | E65: =G14 -> 0 | F65: =E65/$E$56 -> 0 | G65: =I14 -> 0 | H65: =G65/$G$56 -> 0 | I65: =V14 -> 0 | J65: =I65/$I$56 -> 0
B66: E. Private pension contributions | C66: =C15 -> 0 | D66: =C66/$C$56 -> 0 | E66: =G15 -> 0 | F66: =E66/$E$56 -> 0 | G66: =I15 -> 0 | H66: =G66/$G$56 -> 0 | I66: =V15 -> 0 | J66: =I66/$I$56 -> 0
B67: F.i. Investing - lump sum | C67: =C16 -> 0 | D67: =C67/$C$56 -> 0 | E67: =G16 -> 0 | F67: =E67/$E$56 -> 0 | G67: =I16 -> 0 | H67: =G67/$G$56 -> 0 | I67: =V16 -> 0 | J67: =I67/$I$56 -> 0
B68: F.ii. Investing - ongoing | C68: =C17 -> 21.129031 | D68: =C68/$C$56 -> 0.00041555313 | E68: =G17 -> 105.64516 | F68: =E68/$E$56 -> 0.0020777656 | G68: =I17 -> 147.90322 | H68: =G68/$G$56 -> 0.0029088719 | I68: =V17 -> 422.58063 | J68: =I68/$I$56 -> 0.0083110625
B69: G.i. Adjust investments - lump | C69: =C18 -> 498.22256 | D69: =C69/$C$56 -> 0.0097987426 | E69: =G18 -> 1183.9989 | F69: =E69/$E$56 -> 0.02328618 | G69: =I18 -> 1703.9068 | H69: =G69/$G$56 -> 0.033511418 | I69: =V18 -> 11895.482 | J69: =I69/$I$56 -> 0.23395321
B70: G.ii. Adjust investments - continuous | C70: =C19 -> 122.76435 | D70: =C70/$C$56 -> 0.0024144557 | E70: =G19 -> 545.27316 | F70: =E70/$E$56 -> 0.010724106 | G70: =I19 -> 880.14174 | H70: =G70/$G$56 -> 0.0173101 | I70: =V19 -> 7618.5575 | J70: =I70/$I$56 -> 0.14983722
B71: H. Emergency Fund/Child Savings | C71: =C20 -> -1553.6052 | D71: =C71/$C$56 -> -0.030555377 | E71: =G20 -> -1553.6052 | F71: =E71/$E$56 -> -0.030555377 | G71: =I20 -> -1553.6052 | H71: =G71/$G$56 -> -0.030555377 | I71: =V20 -> -1553.6052 | J71: =I71/$I$56 -> -0.030555377
B72: F & G levers combined | C72: =C21 -> 642.11594 | D72: =C72/$C$56 -> 0.012628751 | E72: =G21 -> 1834.9172 | F72: =E72/$E$56 -> 0.036088051 | G72: =I21 -> 2731.9518 | H72: =G72/$G$56 -> 0.05373039 | I72: =V21 -> 19936.62 | J72: =I72/$I$56 -> 0.39210149
B73: I. Refinancing High-Interest Debt | D73: =C73/$C$56 -> 0 | F73: =E73/$E$56 -> 0 | H73: =G73/$G$56 -> 0 | J73: =I73/$I$56 -> 0
B74: J. Consolidating or Paying Off Debt Faster | D74: =C74/$C$56 -> 0 | F74: =E74/$E$56 -> 0 | H74: =G74/$G$56 -> 0 | J74: =I74/$I$56 -> 0
B78: Net wealth deltas/impact from Do-Nothing
C80: 1 Year | E80: 5 Year | G80: 10 Year | I80: 20 Year
C81: abs | D81: % | E81: abs | F81: % | G81: abs | H81: % | I81: abs | J81: %
B82: 0. Do-Nothing (Baseline) | C82: =C31 -> -89181.923 | E82: =G31 -> 280516.71 | G82: =L31 -> 785320.42 | I82: =V31 -> 1851826.4
B83: =Model!B119 -> Meet Financial Goal: Purchasing NE London Property | C83: =C32 -> -22959.258 | D83: =C83/C$82 -> 0.25744295 | E83: =G32 -> 13.600143 | F83: =E83/E$82 -> 4.8482471e-05 | G83: =L32 -> 56455.855 | H83: =G83/G$82 -> 0.071888944 | I83: =N32 -> 88879.911 | J83: =I83/I$82 -> 0.047995811
B84: =Model!B167 -> Meet Financial Goal: Short Term Expenses | C84: =C33 -> -15800 | D84: =C84/C$82 -> 0.17716595 | E84: =G33 -> -15800 | F84: =E84/E$82 -> -0.05632463 | G84: =L33 -> -15800 | H84: =G84/G$82 -> -0.020119176 | I84: =N33 -> -15800 | J84: =I84/I$82 -> -0.0085321172
B85: =Model!B204 -> Meet Financial Goal: Comfortable Retirement | C85: =C34 -> 459.46185 | D85: =C85/C$82 -> -0.0051519617 | E85: =G34 -> 68435.463 | F85: =E85/E$82 -> 0.24396216 | G85: =L34 -> 165525.66 | H85: =G85/G$82 -> 0.21077468 | I85: =N34 -> 208561.84 | J85: =I85/I$82 -> 0.11262494
B86: Meeting goals net wealth impact | C86: =sum(C83:C85) -> -38299.796 | D86: =C86/C$82 -> 0.42945694 | E86: =sum(E83:E85) -> 52649.063 | F86: =E86/E$82 -> 0.18768601 | G86: =sum(G83:G85) -> 206181.52 | H86: =G86/G$82 -> 0.26254445 | I86: =sum(I83:I85) -> 281641.75 | J86: =I86/I$82 -> 0.15208863
B87: A. Increasing Salary | C87: =C36 -> 2160 | D87: =C87/C$82 -> -0.024220155 | E87: =G36 -> 11240.727 | F87: =E87/E$82 -> 0.040071505 | G87: =L36 -> 23651.397 | H87: =G87/G$82 -> 0.030116876 | I87: =N36 -> 28970.114 | J87: =I87/I$82 -> 0.015644076
B88: B. Side hustles and additional income streams | C88: =C37 -> 0 | D88: =C88/C$82 -> 0 | E88: =G37 -> 0 | F88: =E88/E$82 -> 0 | G88: =L37 -> 0 | H88: =G88/G$82 -> 0 | I88: =N37 -> 0 | J88: =I88/I$82 -> 0
B89: C. Reducing Fixed Expenses | C89: =C38 -> 2070 | D89: =C89/C$82 -> -0.023210982 | E89: =G38 -> 10350 | F89: =E89/E$82 -> 0.036896198 | G89: =L38 -> 20700 | H89: =G89/G$82 -> 0.026358668 | I89: =N38 -> 24840 | J89: =I89/I$82 -> 0.013413784
B90: Independent levers net wealth impact | C90: =sum(C87:C89) -> 4230 | D90: =C90/C$82 -> -0.047431137 | E90: =sum(E87:E89) -> 21590.727 | F90: =E90/E$82 -> 0.076967702 | G90: =sum(G87:G89) -> 44351.397 | H90: =G90/G$82 -> 0.056475544 | I90: =sum(I87:I89) -> 53810.114 | J90: =I90/I$82 -> 0.02905786
B91: D. Higher-yield savings | C91: =C40 -> 0 | D91: =C91/C$82 -> 0 | E91: =G40 -> 563.12889 | F91: =E91/E$82 -> 0.00200747 | G91: =L40 -> 2689.9015 | H91: =G91/G$82 -> 0.003425228 | I91: =N40 -> 4042.4213 | J91: =I91/I$82 -> 0.0021829375
B92: E. Private pension contributions | C92: =C41 -> 0 | D92: =C92/C$82 -> 0 | E92: =G41 -> 0 | F92: =E92/E$82 -> 0 | G92: =L41 -> 0 | H92: =G92/G$82 -> 0 | I92: =N41 -> 0 | J92: =I92/I$82 -> 0
B93: F.i. Investing - lump sum | C93: =C42 -> 0 | D93: =C93/C$82 -> 0 | E93: =G42 -> 0 | F93: =E93/E$82 -> 0 | G93: =L42 -> 0 | H93: =G93/G$82 -> 0 | I93: =N42 -> 0 | J93: =I93/I$82 -> 0
B94: F.ii. Investing - ongoing | C94: =C43 -> 21.129031 | D94: =C94/C$82 -> -0.00023692056 | E94: =G43 -> 1513.6439 | F94: =E94/E$82 -> 0.0053959136 | G94: =L43 -> 7264.484 | H94: =G94/G$82 -> 0.009250344 | I94: =N43 -> 11076.038 | J94: =I94/I$82 -> 0.0059811428
B95: G.i. Adjust investments - lump | C95: =C44 -> 3831.3426 | D95: =C95/C$82 -> -0.042960977 | E95: =G44 -> 36030.032 | F95: =E95/E$82 -> 0.12844166 | G95: =L44 -> 117465.54 | H95: =G95/G$82 -> 0.14957658 | I95: =N44 -> 170408.14 | J95: =I95/I$82 -> 0.09202166
B96: G.ii. Adjust investments - continuous | C96: =C45 -> 572.76435 | D96: =C96/C$82 -> -0.0064224265 | E96: =G45 -> 9016.9929 | F96: =E96/E$82 -> 0.032144227 | G96: =L45 -> 43236.822 | H96: =G96/G$82 -> 0.055056281 | I96: =N45 -> 68839.603 | J96: =I96/I$82 -> 0.037173896
B97: H. Emergency Fund/Child Savings | C97: =C46 -> 0 | D97: =C97/C$82 -> 0 | E97: =G46 -> 563.12889 | F97: =E97/E$82 -> 0.00200747 | G97: =L46 -> 2689.9015 | H97: =G97/G$82 -> 0.003425228 | I97: =N46 -> 4042.4213 | J97: =I97/I$82 -> 0.0021829375
B98: F & G levers combined | C98: =C47 -> 4425.2359 | D98: =C98/C$82 -> -0.049620324 | E98: =G47 -> 46560.669 | F98: =E98/E$82 -> 0.1659818 | G98: =L47 -> 167966.85 | H98: =G98/G$82 -> 0.21388321 | I98: =N47 -> 250323.78 | J98: =I98/I$82 -> 0.1351767
B99: I. Refinancing High-Interest Debt | D99: =C99/C$82 -> 0 | F99: =E99/E$82 -> 0 | H99: =G99/G$82 -> 0 | J99: =I99/I$82 -> 0
B100: J. Consolidating or Paying Off Debt Faster | D100: =C100/C$82 -> 0 | F100: =E100/E$82 -> 0 | H100: =G100/G$82 -> 0 | J100: =I100/I$82 -> 0

Sheet Graphs
B2: {=Summary!A3:AZ7} | D2: 46143 | E2: 46508 | F2: 46874 | G2: 47239 | H2: 47604 | I2: 47969 | J2: 48335 | K2: 48700 | L2: 49065 | M2: 49430 | N2: 49796 | O2: 50161 | P2: 50526 | Q2: 50891 | R2: 51257 | S2: 51622 | T2: 51987 | U2: 52352 | V2: 52718 | W2: 53083 | X2: 53448 | Y2: 53813 | Z2: 54179 | AA2: 54544 | AB2: 54909 | AC2: 55274 | AD2: 55640 | AE2: 56005 | AF2: 56370 | AG2: 56735 | AH2: 57101 | AI2: 57466 | AJ2: 57831 | AK2: 58196 | AL2: 58562 | AM2: 58927 | AN2: 59292 | AO2: 59657 | AP2: 60023 | AQ2: 60388 | AR2: 60753 | AS2: 61118 | AT2: 61484 | AU2: 61849 | AV2: 62214 | AW2: 62579 | AX2: 62945 | AY2: 63310
C3: Do-Nothing (Baseline) | D3: 50845.56 | E3: 50845.56 | F3: 50845.56 | G3: 50845.56 | H3: 50845.56 | I3: 50845.56 | J3: 50845.56 | K3: 50845.56 | L3: 50845.56 | M3: 50845.56 | N3: 50845.56 | O3: 50845.56 | P3: 50845.56 | Q3: 50845.56 | R3: 50845.56 | S3: 50845.56 | T3: 50845.56 | U3: 50845.56 | V3: 50845.56 | W3: 50845.56 | X3: 50845.56 | Y3: 50845.56 | Z3: 50845.56 | AA3: 50845.56 | AB3: 50845.56 | AC3: 50845.56 | AD3: 50845.56 | AE3: 50845.56 | AF3: 50845.56 | AG3: 50845.56 | AH3: 50845.56 | AI3: 50845.56 | AJ3: 50845.56 | AK3: 50845.56 | AL3: 50845.56 | AM3: 50845.56 | AN3: 50845.56 | AO3: 50845.56 | AP3: 50845.56 | AQ3: 50845.56 | AR3: 50845.56 | AS3: 50845.56 | AT3: 50845.56 | AU3: 50845.56 | AV3: 50845.56 | AW3: 50845.56 | AX3: 50845.56 | AY3: 50845.56
C4: Meet Financial Goal: Purchasing NE London Property | D4: -33976.56 | E4: -33976.56 | F4: -33976.56 | G4: -33976.56 | H4: -33976.56 | I4: -33976.56 | J4: -33976.56 | K4: -33976.56 | L4: -33976.56 | M4: -33976.56 | N4: -33976.56 | O4: -33976.56 | P4: -33976.56 | Q4: -33976.56 | R4: -33976.56 | S4: -33976.56 | T4: -33976.56 | U4: -33976.56 | V4: -33976.56 | W4: -33976.56 | X4: -33976.56 | Y4: -33976.56 | Z4: -33976.56 | AA4: -33976.56 | AB4: -8000 | AC4: 0 | AD4: 0 | AE4: 0 | AF4: 0 | AG4: 0 | AH4: 0 | AI4: 0 | AJ4: 0 | AK4: 0 | AL4: 0 | AM4: 0 | AN4: 0 | AO4: 0 | AP4: 0 | AQ4: 0 | AR4: 0 | AS4: 0 | AT4: 0 | AU4: 0 | AV4: 0 | AW4: 0 | AX4: 0 | AY4: 0
C5: Meet Financial Goal: Short Term Expenses | D5: 0 | E5: 0 | F5: 0 | G5: 0 | H5: 0 | I5: 0 | J5: 0 | K5: 0 | L5: 0 | M5: 0 | N5: 0 | O5: 0 | P5: 0 | Q5: 0 | R5: 0 | S5: 0 | T5: 0 | U5: 0 | V5: 0 | W5: 0 | X5: 0 | Y5: 0 | Z5: 0 | AA5: 0 | AB5: 0 | AC5: 0 | AD5: 0 | AE5: 0 | AF5: 0 | AG5: 0 | AH5: 0 | AI5: 0 | AJ5: 0 | AK5: 0 | AL5: 0 | AM5: 0 | AN5: 0 | AO5: 0 | AP5: 0 | AQ5: 0 | AR5: 0 | AS5: 0 | AT5: 0 | AU5: 0 | AV5: 0 | AW5: 0 | AX5: 0 | AY5: 0
C6: Meet Financial Goal: Comfortable Retirement | D6: -15315.395 | E6: -15315.395 | F6: -15315.395 | G6: -15315.395 | H6: -15315.395 | I6: -15315.395 | J6: -15315.395 | K6: -15315.395 | L6: -15315.395 | M6: -15315.395 | N6: -15315.395 | O6: -15315.395 | P6: -15315.395 | Q6: -15315.395 | R6: -15315.395 | S6: -15315.395 | T6: -15315.395 | U6: -15315.395 | V6: -15315.395 | W6: -15315.395 | X6: -15315.395 | Y6: -15315.395 | Z6: -15315.395 | AA6: -15315.395 | AB6: -15315.395 | AC6: -15315.395 | AD6: -15315.395 | AE6: -15315.395 | AF6: -15315.395 | AG6: -15315.395 | AH6: -15315.395 | AI6: -15315.395 | AJ6: -15315.395 | AK6: -15315.395 | AL6: -15315.395 | AM6: 50000 | AN6: 50000 | AO6: 50000 | AP6: 50000 | AQ6: 50000 | AR6: 50000 | AS6: 50000 | AT6: 50000 | AU6: 50000 | AV6: 50000 | AW6: 50000 | AX6: 50000 | AY6: 50000
A37: Net Wealth Projections financial goals
B40: 46023 | C40: 46388 | D40: 46753 | E40: 47119 | F40: 47484 | G40: 47849 | H40: 48214 | I40: 48580 | J40: 48945 | K40: 49310 | L40: 49675 | M40: 50041 | N40: 50406 | O40: 50771 | P40: 51136 | Q40: 51502 | R40: 51867 | S40: 52232 | T40: 52597 | U40: 52963
A41: "Do-nothing" | B41: =Summary!C31 -> -89181.923 | C41: =Summary!D31 -> 823.04387 | D41: =Summary!E31 -> 92378.294 | E41: =Summary!F31 -> 185576.5 | F41: =Summary!G31 -> 280516.71 | G41: =Summary!H31 -> 377304.8 | H41: =Summary!I31 -> 476053.94 | I41: =Summary!J31 -> 576885.16 | ... U41: =Summary!V31 -> 1851826.4
A42: Financial Goals | B42: =Summary!C35 -> -127481.72 | C42: =Summary!D35 -> -17160.462 | D42: =Summary!E35 -> 96288.154 | E42: =Summary!F35 -> 213011.63 | F42: =Summary!G35 -> 333165.77 | G42: =Summary!H35 -> 456915.27 | H42: =Summary!I35 -> 584434.17 | I42: =Summary!J35 -> 715906.55 | ... U42: =Summary!V35 -> 2530796.7
A70: Lever A-C Net Income Increase
C71: 46143 | D71: 46508 | E71: 46874 | F71: 47239 | G71: 47604 | H71: 47969 | I71: 48335 | J71: 48700 | K71: 49065 | L71: 49430 | M71: 49796 | N71: 50161 | O71: 50526 | P71: 50891 | Q71: 51257 | R71: 51622 | S71: 51987 | T71: 52352 | U71: 52718 | V71: 53083 | W71: 53448 | X71: 53813 | Y71: 54179 | Z71: 54544 | AA71: 54909 | AB71: 55274 | AC71: 55640 | AD71: 56005 | AE71: 56370 | AF71: 56735 | AG71: 57101 | AH71: 57466 | AI71: 57831 | AJ71: 58196 | AK71: 58562 | AL71: 58927
B72: Increasing Salary | C72: =Summary!C9 -> 2160 | D72: =Summary!D9 -> 2203.2 | E72: =Summary!E9 -> 2247.264 | F72: =Summary!F9 -> 2292.2093 | G72: =Summary!G9 -> 2338.0535 | H72: =Summary!H9 -> 2384.8145 | I72: =Summary!I9 -> 2432.5108 | J72: =Summary!J9 -> 2481.161 | ... AL72: =Summary!AL9 -> 4319.7614
B73: Reducing Fixed Expenses | C73: =Summary!C11 -> 2070 | D73: =Summary!D11 -> 2070 | E73: =Summary!E11 -> 2070 | F73: =Summary!F11 -> 2070 | G73: =Summary!G11 -> 2070 | H73: =Summary!H11 -> 2070 | I73: =Summary!I11 -> 2070 | J73: =Summary!J11 -> 2070 | ... AL73: =Summary!AL11 -> 2070
A98: Net Wealth Projections Levers A-C
B101: 46023 | C101: 46388 | D101: 46753 | E101: 47119 | F101: 47484 | G101: 47849 | H101: 48214 | I101: 48580 | J101: 48945 | K101: 49310 | L101: 49675 | M101: 50041 | N101: 50406 | O101: 50771 | P101: 51136 | Q101: 51502 | R101: 51867 | S101: 52232 | T101: 52597 | U101: 52963
A102: "Do-nothing" | B102: =Summary!C31 -> -89181.923 | C102: =Summary!D31 -> 823.04387 | D102: =Summary!E31 -> 92378.294 | E102: =Summary!F31 -> 185576.5 | F102: =Summary!G31 -> 280516.71 | G102: =Summary!H31 -> 377304.8 | H102: =Summary!I31 -> 476053.94 | I102: =Summary!J31 -> 576885.16 | ... U102: =Summary!V31 -> 1851826.4
A103: Levers A & C | B103: =sum(Summary!C36:C38)+B102 -> -84951.923 | C103: =sum(Summary!D36:D38)+C102 -> 9326.2439 | D103: =sum(Summary!E36:E38)+D102 -> 105198.76 | E103: =sum(Summary!F36:F38)+E102 -> 202759.17 | F103: =sum(Summary!G36:G38)+F102 -> 302107.44 | G103: =sum(Summary!H36:H38)+G102 -> 403350.34 | H103: =sum(Summary!I36:I38)+H102 -> 506601.99 | I103: =sum(Summary!J36:J38)+I102 -> 611984.37 | ... U103: =sum(Summary!V36:V38)+U102 -> 1945708.7
C131: Lever D - H Prioritized by Net Income Impact | D131: £ 5 years (2030) | E131: % | F131: £ 20 years (2045) | G131: %
C132: G.i. Adjust investments - one-time | D132: =Summary!G18 -> 1183.9989 | E132: =D132/Summary!G$4 -> 0.02328618 | F132: =Summary!V18 -> 11895.482 | G132: =F132/Summary!V$4 -> 0.23395321
C133: G.ii. Adjust investments - ongoing | D133: =Summary!G19 -> 545.27316 | E133: =D133/Summary!G$4 -> 0.010724106 | F133: =Summary!V19 -> 7618.5575 | G133: =F133/Summary!V$4 -> 0.14983722
C134: F.ii. Starting to invest/ investing more - ongoing | D134: =Summary!G17 -> 105.64516 | E134: =D134/Summary!G$4 -> 0.0020777656 | F134: =Summary!V17 -> 422.58063 | G134: =F134/Summary!V$4 -> 0.0083110625
C135: F.i. Starting to invest/ investing more - one-time | D135: =Summary!G16 -> 0 | E135: =D135/Summary!G$4 -> 0 | F135: =Summary!V16 -> 0 | G135: =F135/Summary!V$4 -> 0
C136: D. Investing in higher-yield savings | D136: =Summary!G14 -> 0 | E136: =D136/Summary!G$4 -> 0 | F136: =Summary!V14 -> 0 | G136: =F136/Summary!V$4 -> 0
C137: E. Private pension contributions | D137: =Summary!G15 -> 0 | E137: =D137/Summary!G$4 -> 0 | F137: =Summary!V15 -> 0 | G137: =F137/Summary!V$4 -> 0
C138: H. Emergency fund/child savings | D138: =Summary!G20 -> -1553.6052 | E138: =D138/Summary!G$4 -> -0.030555377 | F138: =Summary!V20 -> -1553.6052 | G138: =F138/Summary!V$4 -> -0.030555377
C142: Lever D - H Prioritized by Net Wealth Impact | D142: £ 5 years (2030) | E142: % | F142: £ 20 years (2045) | G142: %
C143: G.i. Adjust investments - one-time | D143: =Summary!G44 -> 36030.032 | E143: =D143/Summary!G$31 -> 0.12844166 | F143: =Summary!V44 -> 604577.3 | G143: =F143/Summary!V$31 -> 0.32647622
C144: G.ii. Adjust investments - ongoing | D144: =Summary!G45 -> 9016.9929 | E144: =D144/Summary!G$31 -> 0.032144227 | F144: =Summary!V45 -> 301198.19 | G144: =F144/Summary!V$31 -> 0.16264926
C145: F.ii. Starting to invest/ investing more - ongoing | D145: =Summary!G43 -> 1513.6439 | E145: =D145/Summary!G$31 -> 0.0053959136 | F145: =Summary!V43 -> 38250.657 | G145: =F145/Summary!V$31 -> 0.020655638
C146: H. Emergency fund/child savings | D146: =Summary!G46 -> 563.12889 | E146: =D146/Summary!G$31 -> 0.00200747 | F146: =Summary!V46 -> 12863.357 | G146: =F146/Summary!V$31 -> 0.0069463082
C147: D. Investing in higher-yield savings | D147: =Summary!G40 -> 563.12889 | E147: =D147/Summary!G$31 -> 0.00200747 | F147: =Summary!V40 -> 12863.357 | G147: =F147/Summary!V$31 -> 0.0069463082
C148: F.i. Starting to invest/ investing more - one-time | D148: =Summary!G42 -> 0 | E148: =D148/Summary!G$31 -> 0 | F148: =Summary!V42 -> 0 | G148: =F148/Summary!V$31 -> 0
C149: E. Private pension contributions | D149: =Summary!G41 -> 0 | E149: =D149/Summary!G$31 -> 0 | F149: =Summary!V41 -> 0 | G149: =F149/Summary!V$31 -> 0

Sheet Questions
A1: Do you have any checking or savings accounts? None have currently been provided
A2: When you say sister is buying you out of home, does this entail she is taking over the mortgage as well?
A3: What share of the downpayment will be coming out of your investments?
A4: Are mortgage payments going to be split 50/50 with your sister?
A5: You mentioned that you are paying 817 for mortgage. Is this in addition to the mortgage monthly payments of 2220.87?
